Workbook

Sheet FMPP
A1: FY | B1: FAIN | C1: Organizaton | D1: Award Amount | E1: Published Project Description
A2: 2022 | B2: AM22FMPPTN1130 | C2: Jonesborough Locally Grown | D2: 150727.83 | E2: Jonesborough Locally Grown (JLG) is a 501(c)(3) non-profit that connects farmers, food, and the community to grow a vibrant local food system. JLG operates two markets: Boone Street Market (BSM), a year-round local foods store, and Jonesborough Farmers Market (JFM), a tailgate farmers market. Both are producer-only that source primarily within 100 miles of Jonesborough, TN. JLG keeps fees low to benefit the vendor and supports over 100 vendors, many of whom are small or beginning farmers. JLG markets operate with significant volunteer support, donations and fundraisers – somewhat unreliable labor and funding sources, as the COVID-19 pandemic demonstrated. For the long-term financial stability of BSM and JFM and viability of JLG vendors, sales must increase to avoid radically changing the low vendor fee structure JLG currently employs. JLG was awarded a FMPP grant in 2018, allowing the start of an intensive marketing campaign. The previous grant was successful despite challenges presented by the pandemic, but rising inflation and overhead costs have increased the sales threshold required to sustain JLG markets. This project builds on the sampling and advertising elements of the previous project – and adds an important consumer demand: online ordering. With FMPP funds to support these initiatives, sales at BSM and JFM are projected to increase 15% by the end of the project period. Increasing sales in addition to foot traffic and retaining vendors are key to the long-term financial stability of BSM and JFM – and, therefore, the sustainability of the farmers and vendors supported by JLG markets.
A3: 2022 | B3: AM22FMPPAZ1133 | C3: City of Winslow | D3: 198392.81 | E3: Through this project, the Mother Road Farmers Market in Winslow, Arizona, will: Develop, coordinate, and expand local direct producer-to-consumer markets; Increase access to locally grown agricultural products; and Support small farms, new and beginning farmers, and/or underserved producers. The project will establish a full-time Farmers Market Coordinator to support current vendors, add additional food vendors (targeting produce), create programs, promote the market to the community, and evaluate project activities. Expected outcomes are to increase the amount of locally grown produce and food products available to residents by adding 10 produce vendors and creating a consignment program; increase income for local growers – with a focus on small, new, and/or under resourced growers; and improve access to fresh, locally grown food for low-income residents, which includes the community’s Indigenous and Hispanic populations.
A4: 2022 | B4: AM22FMPPAZ1134 | C4: Nalwoodi Denzhone: Strength and Beauty Community, Inc. | D4: 231388 | E4: This project will address the economic hardships facing the San Carlos Apache communities by building the Tribe’s capacity of supporting local-food enterprises with direct producer-to-consumer marketing technical assistance. Project activities include creating a marketing plan, the development of regional networks supporting local-food aggregation and distribution, establishing operation policies, food safety plans, standard operating procedures required for a successful direct producer-to-consumer marketing. Project deliverables will be utilized in the provision of targeted technical assistance and training to beginning and socially disadvantaged farmers, ranchers, and food businesses as a form of job/career training for Apache people. Project outcomes include a strengthened regional food economy on the San Carlos Apache Reservation, increased access to and consumption of local food, and job creation spurred by related economic development.
A5: 2022 | B5: AM22FMPPCA1135 | C5: Project New Village | D5: 250000 | E5: The purpose of the People’s Produce Mobile Farmers Market is to bring healthy, fairly-priced, locally-grown produce and other nutritious foods to low-income residents and food assistance beneficiaries using a refrigerated food truck operated by Project New Village, a 501(3)(c) grassroots nonprofit. The project’s service area will encompass eight weekly sites throughout Greater Southeastern San Diego, including the City of San Diego’s Promise Zone, the City of Lemon Grove, and National City. The project will provide a food retail shopping experience to consumers, meeting them at natural points of service such as libraries, YMCAs, community clinics, church parking lots, and other community-oriented gathering spaces. This project will improve equitable access to good food, which Project New Village defines as food that is: sustainable, healthy, affordable, and accessible to all residents. The project will engage new small farmers and producers, conduct culturally-competent marketing activities to market healthy food products and promote food assistance programs, reaching more than 15,000 customers.
A6: 2022 | B6: AM22FMPPCA1138 | C6: Central Coast Ag Network dba City Farm SLO | D6: 249919.95 | E6: “Scaling and Expanding San Luis Obispo (SLO) County Farmer Collaborative Partnerships” will measurably address major local and regional barriers to central coast farmers as well as vulnerable/underserved/ socially disadvantaged (low income- low access) communities relating to equitable and inclusive market opportunities and consumer access. This project will build a Farmer Collaborative that offers sustained supportive services and trainings to empower, and benefit limited resource, beginning, socially disadvantaged, and veteran farmers. In addition, the project will collaborate with Harvestly to expand online sales and Slow Money SLO to integrate farmers with the SLO County Farm to School Program. This project provides capacity needed to unify small-scale, new/ beginning farmers and ranchers, as well as underserved/ socially disadvantaged and veteran producer/ consumer communities. Direct beneficiaries include current and future City Farm SLO tenants participating in the Farmer Collaborative, SLO County Farmers, consumers, school districts, and the regional economy. The project’s work plan acts as a strategic and structural backbone to growing partnerships in a way that enables farmers to share administrative, knowledge, equipment, and other resources. The project also provides farmers access to extensive trainings, toolkits, onboarding, marketing, and support services. It is intended that this project will act as a pilot demonstration that can be rapidly adopted, replicated, and scaled throughout the County.
A7: 2022 | B7: AM22FMPPCA1140 | C7: Jefferson Economic Development Institute | D7: 100000 | E7: The project seeks to strengthen the regional food system infrastructure in Siskiyou County, CA by expanding the Mount Shasta Farmer’s Market and providing development opportunities for the area’s beginning farmers. Through collaboration with other organizations and farmers’ markets, and by supporting the business development of small-scale farmers and producers, this project seeks to strengthen the role of regional farmers’ markets in the direct-to-consumer supply chain while also supporting the development of beginning farmers. Project goals include increasing the number of customers patronizing the Mount Shasta Farmers’ Market, actively integrating beginning farmers/producers into the market, facilitating the creation of new value-added products, providing workshops on subjects identified by project stakeholders, identifying opportunities for regional farmers’ markets to collaborate, and creating new organizations focused on outreach to new customers.
A8: 2022 | B8: AM22FMPPCA1141 | C8: Pajaro Valley Community Health Trust | D8: 198245.2 | E8: This project will sustain and build the capacity of El Mercado, a California-certified, seasonal, and health-centric farmer’s market located in an area with concentrated poverty, limited access to supermarkets or locally grown food, and high rates of health disparities. The project’s goals are to build the long-term organizational capacity of El Mercado by doubling the foot traffic, number of agricultural producers, and average gross sales over a three-year period. Project activities will focus on increasing foot traffic through consumer- centric marketing efforts and community engagement, and subsequently growing the number of participating California-certified agricultural producers. The project will enable the expansion of a direct producer-to-consumer market, increasing access to and availability of locally and regionally produced agricultural products.
A9: 2022 | B9: AM22FMPPCO1136 | C9: Initium Health | D9: 229120 | E9: The project will bring together a multidisciplinary team to Shepard a group of Colorado agricultural producer through a process to identify available consumer markets, assess each operation’s challenges and opportunities, and map a process to successfully reach the market(s) that best fits each operation. Project deliverables include a toolkit for producers to enhance their market strategy within modern marketing frameworks, and a facilitated information exchange between farmers and partners specializing in aggregating and advertising local farm produce. Project outcomes include enabling local farms to maximize their capacity, reach new markets, and expand their presence in incumbent markets.
A10: 2022 | B10: AM22FMPPDE1101 | C10: New Castle County | D10: 125109 | E10: The New Castle County (NCC) Department of Community Services (DCS) will develop, coordinate, and expand direct producer-to-consumer markets, increase producers' economic opportunity, and expand access and availability of locally and regionally produced agricultural products through the acquired Bellevue Farmers Market and its new Reader's Café Farm-to-Table, Farm Fresh Initiative. This project aligns with the NCC DCS' Live Healthy Initiative to provide access to fresh, healthy agricultural food to low-income and low-access (LI/LA) communities while providing a viable market for producers to earn an income. The NCC DCS will use the FMPP funding to develop new market opportunities for and expand direct producer-to-consumer sales opportunities at the Bellevue Farms Market and the Reader's Café Farm-to-Table, Farm Fresh Market. This project will also target outreach, marketing, and promotion to engage new and existing regional and local farmers and producers and promote agricultural products available at the Bellevue Farmers Market and the Reader's Café Farm-to-Table, Farm Fresh Market. The goal is to create new economic opportunities for regional and local farmers and producers by recruiting new and established repeat customers through partnerships and community engagement with USDA LI/LA Census Tracts, other low-income communities, and the general public. The NCC DCS is committed to increasing consumption and access to locally and regionally produced agricultural products, as demonstrated through years of experience engaging producers at its weekly farmers markets throughout New Castle County.
A11: 2022 | B11: AM22FMPPFL1117 | C11: Village of Wellington | D11: 68864 | E11: The Village of Wellington will use grant funding to improve the promotion and marketing of the Lakeside Market at Wellington Town Center Farmers Market. The goals for the Wellington Farmers Market Project are to increase the farmers market attendance, increase the number of vendors, improve the cultural diversity of those vendors, and engage the public through more active participation in healthy educational presentations.
A12: 2022 | B12: AM22FMPPFL1126 | C12: Clara White Mission | D12: 249813.18 | E12: The Clara White Mission (CWM) will use FMPP Capacity Building grant funds to support their efforts to expand a regional farmers market network and training program at the Mission’s agritourism destination in Northwest Jacksonville, White Harvest Farms (WHF). The White Harvest Regional Farmers Market will strengthen local food system infrastructure in a food desert community. This project will include up to 50 local farmers, ranchers, and regional food stakeholders to sell in-person at the farmers market, online and stock products in a retail space. This project builds a regional network of farmers for marketing goods direct-to-consumer and increases market opportunities for farmers, ranchers, and regional food stakeholders. The program will also expand CWM training in food safety.
A13: 2022 | B13: AM22FMPPGA1127 | C13: Retaaza | D13: 152093 | E13: Retaaza will build a new supply chain pathway (infrastructure) in rural Southeast Georgia. Our project establishes a Mobile Market to change the food landscape in Clinch and Ware counties, serving as a much-needed oasis in a food desert to overcome barriers to healthy eating and increase access to fresh foods in pockets of extreme poverty. Local farmers are also important piece of the solution, to achieve the mission of connecting hungry Georgians to available local foods. Families will have healthy options available to them without the limitation of lack of transportation and farmers will be able to increase their income by selling produce that previously went to waste
... A170: 2024 | B170: FMPP24001894 | C170: Cornell Cooperative Extension of Nassau County | D170: 99728.07 | E170: The goal of CCE Nassau’s Eat Local - Shop Local Promotion Program is to spread awareness of the benefits eating and shopping locally-grown and sourced foods has on individuals, local businesses, and communities, and will serve to support the promotion of the CCE Nassau Farmers Market, as well as other avenues for Long Islanders to access farm fresh and local food and goods.

Sheet LFPP
A1: FY | B1: FAIN | C1: Organizaton | D1: Award Amount | E1: Published Project Description
A2: 2022 | B2: AM22LFPPCA1115 | C2: AG Link, Incorporated | D2: 500000 | E2: Ag Link’s 2022 FMPP Marketplace grant project will meet the needs of local producers to sell their farm fresh products directly to consumers through a new roadside stand and innovative online solutions in collaboration with an established supply chain partner. The goals of this project are to increase the numbers of local producers engaged in direct to consumer marketing; connect consumers to local producers for products and farm information and provide an innovative marketing and distribution channel for farmers to engage their social networks to sell their products directly to consumers. The purpose of this grant project is to develop new market opportunities for local producers to sell directly to consumers through development of a new retail stand in addition to an online farmers market. The project will increase returns for farmers making their operations more sustainable by increasing consumption of and access to local products by consumers benefiting the local economy. This project will expand Ag Link’s local food business from wholesale distribution to schools to include direct support of local producers, selling new value-added products directly to consumers.
A3: 2022 | B3: AM22LFPPCA1094 | C3: North Coast Growers' Association | D3: 410722 | E3: North Coast Growers’ Association (NCGA) will work with local/regional food producers to implement a distribution hub that will make it possible for producers to market and distribute their food more efficiently and economically while retaining brand and location identity. “Harvest Hub” will increase market access for producers, supporting their economic vitality by linking them with institutional buyers and other wholesale markets, as well as assessing and addressing producer needs in terms of technology, marketing, and infrastructure for storage, packaging, and distribution to facilitate their participation in wholesale markets. NCGA will engage Humboldt County Office of Education (HCOE) to transition their local food purchasing to the Harvest Hub. New systems for ordering and distribution will be developed and piloted so that Harvest Hub will procure local food for Humboldt County school districts’ meal purchasing programs. NCGA will work with Cal Poly Humboldt (CPH), a CA State University campus, to identify barriers to their local food purchasing goals. Funds from this grant will be used to map needs and barriers of CPH, collaboratively create a plan to update policies and standard operating procedures to overcome these barriers and begin to source locally grown and raised food to help meet their local purchasing goals. The Harvest Hub will benefit local farmers and students. Farmers will be able to increase their markets without increasing costs or workload. Students will have more access to nutrient dense produce throughout the school year to connect them more deeply with their local food system.
A4: 2022 | B4: AM22LFPPCA1105 | C4: Fiery Ginger Farm, LLC | D4: 500000 | E4: Fiery Ginger Farm, LLC was established in West Sacramento, CA in 2015. From the beginning, our intent has been to grow the highest quality produce for school kitchens. Small farmers recognize firsthand the benefits of stable institutional markets. The grant will use the knowledge and relationships that have been built over the last seven years to continue to open the door for other small farmers to gain access to institutional markets. The grant will continue to develop market connections and forward contracts while also providing logistical support, technical assistance, and training for both farmers and food service personnel.
A5: 2022 | B5: AM22LFPPCA1138 | C5: Old Grove Orange, Inc | D5: 432873 | E5: Old Grove Orange’s Expanding Local Food Systems project aims to increase economic opportunity for local farmers, including new/beginning and BIPOC farmers, by connecting them to a growing network of institutional markets in the Inland Empire. As the farmer-pioneer of California’s Farm to School movement, Old Grove Orange (OGO), a farmer-led food hub, has over 16 years of experience connecting a roster of 40+ local farmers to a Farm to School market of 200,000+ students. However, despite a steady increase in demand for fresh, local produce in this region, small farmers continue to struggle to provide the quantities or variety needed by institutional buyers, develop the unique Covid-era food processing/packaging sought by institutional buyers, and obtain the food safety certifications recognized by institutional buyers.This project will allow OGO to upgrade its infrastructure and enhance the processing, aggregation, distribution, and the development of the value-added agricultural products requested for by itsinstitutional clients; to broaden OGO’s customer base by developing new institutional markets for local food products; and to recruit, support, and provide more local farmers with access to institutional buyers. By investing in these three areas, Old Grove will be able to support at least 10 new farmers, increase sales of local agricultural products by 35%, and develop 10 new markets in the form of K-12 public school districts, university cafeterias, and local restaurants.
A6: 2022 | B6: AM22LFPPKY1159 | C6: God's Pantry Food Bank, Inc. | D6: 465658.56 | E6: God’s Pantry Food Bank (GPFB) serves 50 counties in Central and Eastern Kentucky, supporting more than 450 member food pantries and meal programs. Their total food distribution of 41.8 million pounds in 2021 included 13 million pounds of fresh produce. With team partners Appalachian Regional Healthcare (ARH) and Kentucky Educational Development Corporation (KEDC), GPFB is coordinating efforts to increase farm to institution distribution in southeast Kentucky, anchored by the food warehouse GPFB is developing in Hazard. GPFB’s planned facility will serve as a satellite distribution facility to improve food supply to member pantries in the distressed seven-county area. This facility will also provide supply chain infrastructure supporting farm-to-institution initiatives currently underway at ARH and KEDC. Anchoring efforts to supply more fresh fruits, vegetables, and other foods from local and regional sources, this facility will improve nutrition for patients, students, employees, and the community at large. GPFB’s food warehouse, with dry and cold storage, will fill an important gap in the regional food system, currently served by facilities located up to 230 miles away.
A7: 2022 | B7: AM22LFPPMT1119 | C7: Livingston Food Resource Center | D7: 300000 | E7: Livingston Food Resource Center (LFRC) project will promote and support Park County, Montana’s local food system through expanding access to and availability of locally produced foods for regional residents. As a leader in the community, LFRC has the ability to promote and support the local food system by increasing aggregation, processing, and distribution of local produce through: 1. expanding LFRC’s aggregation of local and regional food products to support local food systems; 2. creating value-added agricultural products through the processing of local produce for distribution through the LFRC; 3. increasing the distribution of agricultural products and value-added agricultural products in the region through increasing the capacity of the LFRC’s current programs, including meal and product distribution programs serving pre-K-12 students, seniors, oncology patients, and low-income individuals and families; 4. utilizing LFRC’s Community Bakery and Community Kitchen to further connect and strengthen the relationships between local producers and local food entrepreneurs while supporting the development of strategies to increase the inclusion of local food products in institutional settings to create growth in the local retail food market and economy; 5. and supporting new and established farmers and ranchers to help them succeed and to keep produce local; During this grant period of 9/30/2022 to 9/29/2025, LFRC will source an additional $300,000 of produce and meat from local farms. This project will be sustained after the grant through expanding operations, increasing local food access and demand, and furthering sustainability of the local food system.
A8: 2022 | B8: AM22LFPPMT1179 | C8: Lake County Community Development Corporation | D8: 491701.55 | E8: Institutional markets are increasingly seeking out local and responsibly grown food to add to their food service menus. The Northwest Food Hub Network, a collaboration between three food hubs in Montana and Washington, was created to help respond to these institutional market demands by providing one ordering platform in which institutions can access large quantities of local and regional products. However, the food processing capacity within the Network is limited, and institutions are continuing to ask for value-added food products that are easily integrated into their food operations. This project builds on the success of the Northwest Food Hub Network by increasing the processing capacity for the NWFHN, identifying and creating value-added food products for the institutional marketplace, creating effective marketing materials for the developed products, and providing necessary technical assistance and trainings for local and regional food processors. Mission West will work collaboratively with partners including Kitchen Sync Strategies and Montana State University Food Lab to complete these project objectives. This project will lead to increased sales for the NWFHN, which will ultimately benefit the 211 small to mid-size family farms that are connected to the Network, and will develop best practices for processing and product development that will be shared with interested organizations nationwide.
A9: 2022 | B9: AM22LFPPNC1140 | C9: Working Landscapes | D9: 499951 | E9: This project represents an unprecedented collaboration among five mission-driven food processors, seven food hubs, and 75 farmers and fishermen. Together, these partners will supply 41 North Carolina institutions with a wider array of value-added, locally- sourced foods than they have previously been able to purchase. Each of the 24 products developed and marketed, including fresh-cut produce; pasture-raised chicken, pork, and beef; seafood; and heat-and-serve meals, will be designed for ease of use in institutional kitchens. A subaward will support the development and production of shelf-stable fruit jerky, a wholesome, locally-sourced alternative to the unhealthy snacks offered through after-school programs, summer meals, and other institutional programs.
A10: 2022 | B10: AM22LFPPNC1175 | C10: Farmer Foodshare--DONE | D10: 499949.2 | E10: Farmer Foodshare will grow, diversify and expand our Food Hub by executing a post-pandemic revitalization project aimed at the development, coordination, and expansion of local and regional food business enterprises to increase access to and availability of locally and regionally produced agricultural products in the rapidly growing and agriculturally productive “Research Triangle” region of North Carolina. This project is designed to support this important program through strategic regrowth designed to scale up to pre-pandemic levels, while also diversifying our farmer network and updating operations and sales strategies for a post-pandemic world. Project Activities include: a marketing and outreach campaign; optimizing internal operations; identifying and adopting new software; food safety technical assistance to producers; intentional relationship-building with our farmers; broad partnerships with area food system service providers and institutional buyers; and extensive data collection, evaluation and dissemination. Deliverables and Expected Outcomes: These include expanding the number of farmers to 75 (+88%) and increasing volume of Food Hub purchases to $1 M+ annually by Yr. 3 (+158%); increasing the number of Food Hub buyers to 75 (+88%) and the volume of sales to $1.5 M annually (+158%); building a greater capacity to sustainably support the availability of regionally produced agricultural products and the development, expansion, coordination, and expansion of local and regional food businesses; creation of a robust set of refreshed brand assets and marketing tools to recruit farmers, promote their products; and educate nearly 200K area residents with information about accessing and using locally grown food products; and increasing capacity of FFS to serve farmers and local food institutional buyers by developing and institutionalizing data collection tools and practices for measuring Food Hub success. Intended Beneficiaries: There will be 199,670 direct beneficiaries, plus tens of thousands of customers and clients of our institutional buyers who will benefit from the increase in fresh, local, nutrient dense proteins and produce sourced through increased buying relationships throughout this project. 75 farm businesses will benefit, to the tune of $2.7 M returned to them OMB Number: 4040-0019 Expiration Date: 02/28/2022 * Project Abstract (Continued from previous page) in sales. 75 institutional buyers will benefit through $3.9 M in local food procurement to serve their clients and customers. Additionally, these activities will set Farmer Foodshare up to be sustainable in the long run, continuing to support our stakeholders in the years to come. Sub Recipient Activities: This project does not have sub awards; however it does have contractual partners. They include Carolina Farm Stewardship Association: will provide technical assistance to up to 12 farmers in applying for and securing their GAP certifications, including: coaching and instruction to provide direct TA, helping identify sustainable growers who may be eligible/interested in receiving this TA, with the goal of joining the FFS Farmer Network and accessing new sales markets. Mesh, our marketing consultant, will develop a flexible marketing and outreach campaign toolkit with brand assets, messaging, digital collateral, and customizable templates for content. Farm Fare, our Food Hub Operations & Software Consultant, will review FFS’s operations, and provide Food Hub operations optimization consulting to improve the daily functionality of FFS’s systems; and provide technical assistance for software adoption and implementation. Food Insight Group (FIG), our evaluator, will provide farmer survey question development, process evaluation, Survey and/or in-depth interview development, piloting, and implementation; Impact measurement; Data analysis; and annual reports. Black Farmers Market, will help FFS identify and connect with farmers of color who may be interested in learning about opportunities to sell their products through FFS’s Food Hub.
A11: 2022 | B11: AM22LFPPNH1173 | C11: University System of New Hampshire DONE | D11: 351053 | E11: To increase farm sales to institutions, a variety of approaches will be taken that create opportunities and programs for farms, food hubs and institutions to more easily develop buying/selling relationships. The project leverages opportunities like the new NH Food Hub Network, the relatively new Seacoast School Buying Group and interest in value added product development by two NH businesses. The NH Food Hub Network coordinator, also a new position, will be assisting in coordinating farm to institution sales. This project will also build on the established NH Harvest of the Month program by increasing the variety of monthly offerings making it easier for more farms and institutions to adopt the program, developing appropriate educational and marketing materials for all types of institutions and making the program relevant to the refugee and immigrant populations who now call NH home. Expected outcomes will increase availability of local food products on institutional menus through expansion of HoM and school buying group bids, develop, market, and distribute locally produced value added products for the institutional market and increase demand for locally produced foods by institutions working towards state and regional targets for institutional purchasing and farm production.
A12: 2022 | B12: AM22LFPPVT1096 | C12: Food Connects, Inc | D12: 286280 | E12: The overall goal of the project is to innovate in the supply chain to increase institutional, local food purchasing in Food Connects’ tri-state central New England service area. In 2021, Food Connects recognized the need to focus on institutional sales channels for our small and medium-scale New England producers. Activities to be performed include. but are not limited to, creating and printing marketing materials customized and co-branded to our customers' specs, with the goal to more deeply support customers in their efforts to tell their local food sourcing story, developing a product catalog (print and digital) to improve conversion rate with prospective institutional customers, especially major institutions, distribution of Annual Harvest of the Month calendars, posters, and other educational materials, collaborating with regional partners to support states in developing and improving local purchasing incentive programs for K-12 schools, and executing comprehensive sales push across the current service area to onboard institutional accounts whose food safety requirements Food Connects will be prepared to meet as of Fall 2022. Food Connects will also onboard and serve new institutional customers on new, to-be-launched delivery routes to underserved areas across Southeastern VT, Central, and Eastern MA, with a focus on major accounts, sell products from newly-onboarded suppliers to current customers, scout and onboard new regional suppliers with product offerings that fill important gaps in institutions' local food sourcing programs, develop a forward contracting model for supply, to align the needs and constraints of prospective major institutional customers with regional supply, build and execute a formal, forward-contracted, full-school-year Harvest of the Month local foods sourcing program for schools and colleges, and work with current major suppliers to identify opportunities to further tailor product offerings to the institutional foodservice market. Outcomes for this project include but are not limited to increasing the total number of products that may have success in reaching school customers based on specifications for key staples by 25, developing a product list to share with 30 key school customers to gauge interest, collecting feedback and begin planning for purchase and delivery, and increasing regional food sales to institutions from ~$300,000 in 2021 to $1 million by 2025. Additional outcomes include ensuring stakeholders gain technical knowledge about accessing regional foods and increasing the number of market access points that establish and increase engagement with regional producers.
A13: 2022 | B13: AM22LFPPWV1147 | C13: Yuraction Faction LLC DBA WV Harvest | D13: 482215 | E13: West Virginia Harvest (WVH) is a social enterprise, specialty food brand focused on positively impacting the local food system through innovative local products and services. The WV Harvest Farm to Institution application will connect producers and growers with state institutions through collaborative partnerships that result in stronger local food system in WV. WV Harvest will engage with the current growers, producers, and processors in the state of WV to begin the strategic aggregation of locally grown/raised/produced food products under the WV Harvest Brand. This includes creating an institution focused coordinated food chain and mid-tier value chain, purchasing locally grown/raised/processed products, and aggregating/storing locally grown/produced products in a central location. In addition, WV Harvest will expand on current work by informing the nutritional directors in K-12 and purchasing managers at WV State Institutions about the large selection of fresh and value-added food products available for purchase. This includes developing strategies and action tools for key decision makers of state institutions to become more informed of locally available products through WV Harvest. WV Harvest will market the opportunities for job creation and community growth associated with purchasing locally raised/grow/produced food products to students and administrators to elevate the local food system in WV. This includes informational displays and marketing installations in schools and institutions of higher education.
... A171: 2024 | B171: LFPP24001871 | C171: Board of Regents, NSHE, obo University of Nevada, Reno | D171: 88482.34 | E171: The Desert Farming Initiative is applying on behalf of the Nevada Farm Network to fund a two-year turnkey recruitment and training project, Enhancing Nevada Food Chain Initiatives. DFI will coordinate enhancement actions with partner programs, and facilitate a Leadership Committee made up of local producers and food entrepreneurs to strengthen connections between farmers and the mid-tier value chain. This proposal will leverage and expand on at least four other programs, including the Nevada Small Business Development Centers Made in Nevada e-commerce platform, the Transition to Organic Partnership Program, the Nevada Farm Apprenticeship Program, and the Local Food Network's Nourish and Flourish Non-Profit Commissary Kitchen. The Nevada Farm Network is the first online community of practice for Nevada farmers to access educational resources and make market connections. This project will additionally provide for a pilot project of value-add and processing trainings held at the Local Food Network's kitchen in urban Reno and partner organizations in rural Fallon.

Sheet RFSP
A1: FY | B1: FAIN | C1: Organizaton | D1: Award Amount | E1: Published Project Description
A2: 2022 | B2: AM22RFSPVA1058 | C2: Health Care Without Harm | D2: 999524 | E2: For more than a decade, the Farm to Institution (F2I) movement in Oregon has made significant strides engaging and coordinating efforts of institutional purchasers, government agencies, nonprofit organizations, and supply chain producers and processors. While successes have helped create lasting change in many institutions, the impact of these resources and partnerships has largely been focused on the Portland Metro Region. While almost 100,000 meals per day are served in institutions in the Portland area, there are more than twice as many meals served in institutions throughout the State. The purpose of this project is to leverage existing proofs of concept in farm to institution (F2I) and take them to scale at a state level. F2I will be catalyzed in different regions and rural areas of Oregon by establishing the Oregon Farm to Institution Collaborative (OFIC). Project objectives include Reconfigure the structure of a community of practice focused on F2I Strengthen regional infrastructure to support F2I projects that improve market channels for producers Address gaps and barriers identified in F2I work that contribute to inequities in the food system Develop a shared vision, common language, and purchasing standards for OFIC Key activities to be performed Design a recruitment strategy grounded in equity and inclusion principles and structure for OFIC Convene quarterly OFIC meetings Organize affinity groups, based on institutional setting, regions, and or topics of interest Hire two value chain coordinators in Oregon Hold four regional trainings to food service institutions, value chain coordinators, and producers Complete a land suitability study to determine institutional land for use in F2I projects Disseminate lessons learned and share impactDeliverables and expected outcomes Increase in the number of local producers that are connected to institutional market opportunities. By the end of the project, 200 local producers will have gained knowledge about new market opportunities through education and training. Pilot a farm to hospital project connecting producers to suitable land for food production. By the end of the project, five new or underserved farmers will have institutional land access for farming, and will have support related to food safety certifications and or business plans to meet institutional needs. Institutions will gain clarity on values based procurement. By the end of the project, 400 institutional partners will be reached through activities and communications from OFIC. Intended beneficiaries This project will benefit Oregon producers and processors through improved value chain coordination and connections to new institutional markets, thus providing institutions with more options and streamlined processes to purchase local and meet values based purchasing goals. Additionally, the project will benefit communities served by institutions throughout Oregon, like students, patients, and state employees, who will have improved access to healthy, locally grown and produced food.Subrecipient activities Partner organizations will participate in OFIC and affinity group processes and activities. Advisors and consultants will provide specific expertise and support, such as communications strategy, value chain coordination, product development technical assistance, meeting and group facilitation, and topical trainings (ex food safety, business planning). Producers will participate in the land suitability study and pilot project, or in other projects and activities of the OFIC.
A3: 2022 | B3: AM22RFSPCA1047 | C3: Siskiyou County Economic Development Council | D3: 353442 | E3: The agricultural economic sector in Siskiyou County is facing dire crisis due to persistent drought, year over year wildfires, and environmental pressures faced by small farms. This, paired with major market shifts, is culminating in the urgent decision for small farms across Siskiyou to innovate or exit. Siskiyou Economic Development Council (SEDC) is pairing with key partners throughout Siskiyou and the greater region to launch an initiative to expand market opportunities for Siskiyou producers. These efforts will create opportunities for farms to diversify and create business resiliency in the face of catastrophe. Connecting Siskiyou s Small Farms and Institutions will establish a critical network of local farms and regional institutional food buyers throughout Siskiyou County and its bordering communities. Through one on one technical assistance, SEDC will work to develop business plans and strategies that will connect key stakeholders and identify gaps in necessary infrastructure to cultivate a thriving farm to institution economy. This project will provide technical assistance to producers to develop capacity, skill and scale to address the institutional markets and will cultivate a strong foundation for ongoing connections between buyers and small farms. This program will build upon the SEDC s work in the agriculture sector and community food system and will leverage existing relationships with agricultural producers, support organizations, and expert business consultants. This program will strengthen the institutional local food system, identify gaps in infrastructure and supply chain partners, and connect local small farms to viable new markets in an effort to create long term sustainability for one of Siskiyou s most important economic sectors.
A4: 2022 | B4: AM22RFSPIA1061 | C4: Practical Farmers of Iowa | D4: 861356 | E4: Farmers of Iowa, Kitchen Table Consultants, and Iowa Valley RCAND D to preserve and significantly scale the institutional markets food hubs have developed in Iowa. This project will expand food hub capacity to capture more institutional sales, onboard new farmers, and grow sales territory to equitably serve more of the state. Our work will also leverage upcoming, short term institutional purchasing incentives to convert new institutions to permanent local food customers, transforming the scale of farm to institution in Iowa. Because of FarmTable Procurement AND Delivery s centrality to Iowa s local food system, the food hub network, and to farmers across Iowa, the partnership shares a commitment to transitioning the FarmTable food hub to a non profit and ensuring its long term sustainability. As a support partner with a strong state wide farmer network, Practical Farmers of Iowa (PFI) will provide key outreach and education for farmers to learn about food hubs and become food hub vendors. PFI will also administer and evaluate this project. Iowa Valley RCAND D will facilitate continued spaces for food hubs to collaborate with each other, while key experts at Kitchen Table Consultants will optimize food hub KPIs and provide business management coaching. Food Hub partners will maximize their added capacity made possible by this project, along with technical assistance, to add more farmer vendors, institutional customers, and territory to their individual businesses and expand the footprint of farm to institution in Iowa.
A5: 2022 | B5: AM22RFSPKY1063 | C5: The Kentucky Horticulture Council Inc. | D5: 689908 | E5: Grow Up Expanding Kentucky s regional produce market opportunities is an integrated systems approach that will expand Kentucky s regional food system impact by focusing on production, processing, distribution, and consumption of produce crops. We will leverage a public private partner network to increase production and market literacy while reducing known production and market barriers to support farms, businesses, and entrepreneurs that grow, store, process, market, and distribute produce locally and regionally. With focus and intentionality, the multi disciplinary project team will collectively address needs of at least 2,500 producers, 10 distribution partners, 43 institutional buyers, and 75,000 consumers of food products, with resulting system benefits including increased opportunities across market channels, economic improvement, job creation, enhanced ecosystem services, and expanded access to healthy food.
A6: 2022 | B6: AM22RFSPMA1035 | C6: TSNE MissionWorks, fiscalsponsor of Farm to Institution New | D6: 968375 | E6: This project invests in strengthening regional, equitable farm to institution (FTI) relationships and value chains in three New England Communities, which in coordination will lead to greater regional and values based food procurement across New England while shifting institutional power dynamics around race. Springfield, MA New Haven, CT and Cumberland County, ME will form a Cohort, represented by three community based organizations Springfield Food Policy Council, Cumberland County Food Security Council, City of New Haven Food System Policy Division who are already driving food systems change at the local level. Each of the community organizations will receive subawards to carry out their local organizing, community engagement, and value chain coordination activities. The partnership will be supported by three state departments of agriculture, who will connect partners to additional collaborators and technical assistance. Farm to Institution New England, a regional network backbone organization, will provide project coordination, connect the cohort with regional partners, resources, and trainings, and share stories and strategies developed in each community with the broader network. We believe that strong, inter woven and community driven foundations of FTI work lead to sustainable regional impact for New England producers and residents who eat at institutions. Three objectives drive this project 1. Community level Plan and implement multi sector community driven farm to institution initiatives in three New England communities, ensuring authentic engagement with residents who are most affected by this work and prioritizing disinvested communities. 2. Cohort level Establish a cohort among three communities for peer to peer learning, capacity building, and cross cohort leveraging. 3. Regional level Reinforce and grow New England s farm to institution movement by creating a dynamic and multi directional exchange of promising practices, success stories, and relationship building opportunities between the community cohort and the broader New England network.
A7: 2022 | B7: AM22RFSPMI1039 | C7: Groundwork Center for Resilient Communities, Inc | D7: 891100 | E7: Resilient Relationships, Resilient Supply builds upon established partnerships to strengthen the food system in lower Michigans Western Lakeshore Region to increase sales and consumption of locally grown foods from small and mid sized producers to schools, early child care and education (ECE) centers and emergency food providers The project increases community nutrition security by increasing access to healthy, local food for low income children, families, and citizens. We will support 34 stakeholder partners in filling gaps they have identified in infrastructure and supply chains to help markets grow. We will leverage MIs innovative state program, 10 Cents a Meal for Michigans Kids AND Farms, currently funded at 4.5 million, increasing local food purchasing power for schools, ECE centers, and eligible organizations feeding children via USDA child nutrition programs. Partners will leverage proven regional farm to food pantry initiatives that have grown in response to COVID 19. Lead partnersGroundwork Center for Resilient Communities, the principal of a food processing association, a supply chain logistics expert, and a local foods marketing enterprise with vast farmer connectionswill convene 5 Peer Learning Networks (PLNs) and provide farm to institution support and technical assistance to create stronger collaborations among 5 key stakeholder groups producers, distributors, processors aggregators, schools Early Care and Education (ECE) centers, and emergency food providers (EFP). The PLNs will provide the chance to network, identify needs, find opportunities and solutions, and build relationships. PLN members will attend Learning Journeys to PLN member sites to share best practices. They will have scholarships available to 5 key MI based food systems conferences to build knowledge and gain professional development. Implementation leads in the West MI and NW MI regions will match schools and ECE centers and EFP s to small and mid size farms and related food infrastructure, assisting partners in leveraging existing funding like 10 Cents a Meal and expanding upon farm to pantry initiatives. Subawards will go to 5 partner Core Team Members involved with the project West MI Food Processing Association will serve as Aggregation and Processing PLN Lead, EFP Implementation Lead and School Implementation Lead in 5 county west MI region, and provide Aggregation and Processing technical assistance Alden Services will serve as Distribution PLN Lead and provide Distribution Logistics technical assistance Taste the Local Difference will serve as Producer PLN Lead and also provide marketing technical assistance. Others Northwest Education Services will serve as School Implementation Lead in 5 county Grand Traverse Region Kent Co Essential Needs Task Force will serve as EFP Implementation Lead and School Implementation Lead in Kent Co. The roles they play are crucial for the execution of project objectives. Each offers expertise in their respective domains and are geographically located in regions that expand the reach and benefit of the project. Through technical assistance and coordinated efforts such as writing grants and obtaining loans we aim to increase capacity, develop new market opportunities for producers to expand local and regional food business enterprises, and promote food safety practices to ensure a safe and productive local and regional food system. 501,620 expected beneficiaries of this project include students in schools and ECE centers participating in 10 Cents a Meal, families and low income individuals utilizing EFPs, small and mid size farmers, processors, aggregators, distributors and businesses along the value added supply chain across the 16 county project region. We expect that our efforts in bringing together and engaging stakeholders of the food supply chain with lead to increased resilience and efficacy of work within the regional food system of MI s Western Lakeshore region.
A8: 2022 | B8: AM22RFSPOH1055 | C8: Cuyahoga County Board of Health | D8: 700000 | E8: Feed Our Future Planning, Partnerships and Projects to Increase Local Food Spending leverages local and regional partnerships to advance the collaborations necessary to build a regionally innovative and responsive farm to school (F2S) initiative that serves school aged children across Northern Ohio. The Cuyahoga County Board of Health (CCBH) serves as the backbone organization for Feed Our Future (FOF) Local Foods for Growing Minds, convening individuals and stakeholders throughout Ohio to advance the policy, environmental and systems changes needed to drive systemic change and build a more resilient food system. The project goals are to strengthen the mid tier value chain and increase local and regional food procurement by K 12 school districts. The key objectives of this partnership are to 1) strengthen the mid tier value chain to effectively serve K 12 school systems by increasing the number of producers in the supply chain 2) increase local food purchasing by K 12 school systems through the execution of a farm to school bid 3) increase the knowledge and skills of school meal program staff to menu, serve, and teach about local foods through the creation of two new curriculums and 4) expand organizational capacity to support regional local food system efforts, planning, partnership, and advocacy by hiring an equity consultant, facilitating ongoing meetings of the Feed Our Future Leadership Council, and engaging in new and enhancing existing partnerships to generate a regional farm to school strategic plan. The intended beneficiaries of this proposal include 1) local food system partners in Ohio, including 2 food hubs, 14 existing farm to school producers and local food business, and 5 10 new local food producers and businesses 2) K 12 school systems across a 38 county region in Northern Ohio 3) students attending urban, suburban, and rural school districts across a 38 county region in Northern Ohio and 4) engage 9 existing Feed Our Future Leadership Council member organizations and up to 40 new partners organizations. The activities outlined in this funding proposal require strong collaboration amongst a diverse set of partners. As such, the CCBH will subaward with the following partners to achieve project deliverables Verge Impact Partners (VIP). To provide technical assistance and build the capacity of FOF to design and carryout the work in ways that advance equitable outcomes for children, growers, and producers, on the bases of race, geography, and income. VIP currently serves as the equity consultant to Ohios Farm to Early Care and Education network. Pisanick Partners, LLC (PPLC). To create the Local Foods 101 and Local Menu Takeover 2.0 curriculums. PPLC has provided school nutrition consulting services to FOF since 2015.Local Food Connection (LFC). To co convene the Local Food System Taskforce. LFC will provide strategic direction and logistics coordination for the value chain. Oberlin Food Hub (OFH). To co convene the Local Food System Taskforce. OFH will serve as the value chain coordinator for K 12 schools. Muse Content Group (MCG). To provide the marketing and communication tools necessary to build and strengthen the regional food economy. MCG has served as the paid media partner for FOF since 2015. Ohio Schools Council (OSC). To co convene the School Foodservice Taskforce and work in partnership with CCBH to innovate a F2S procurement bid. OSC has partnered with CCBH on a F2S bid since 2015.
A9: 2022 | B9: AM22RFSPAZ1050 | C9: Pinnacle Prevention | D9: 475471.79 | E9: The purpose of the Implementing a Vibrant, Sustainable, and Equitable Community Food System Across the Arizona Food Systems Network (AZFSN) RFSP implementation and expansion project is to advance the implementation of the AZFSN Statewide Food Action Plan priorities, goals, objectives, and strategies for action. The intended project goals are to 1) strengthen capacity to support plan implementation, and 2) deepen connections across existing partners to institutionalize strategies for each plan priority area. Deliverables include 1) Convening the advisory team of the network to guide the implementation process ensuring representation across the diverse geography and communities of Arizona 2) Engaging network partners in participating and guiding the implementation of the action plan through virtual and in person convenings 3) Building capacity of partners to engage historically underserved communities and regional food producers otherwise isolated from the larger food system efforts in planning implementation efforts 4) Deepening relationships and participation in the partnership with rural and Indigenous food producers and communities with limited local food access by working with community champions that are trusted members of underserved communities 5) Hosting listening sessions with community voices from historically underserved communities and with local food producers, distributors and retailers to identify gaps and co design their local food system response to inform institutional response to meet these needs 6) Evaluation, sharing, and disseminating process outcomes across the implementation process to co design the next multi year food action plan 7) Working iteratively with local coalitions and partners to evaluate the effectiveness of the implementation and expansion work 8) Establishing shared measures and a platform to monitor progress and transparency in the implementation of activities and work 9) Sharing project results and best practices across state agencies, philanthropic partners, local coalitions and local governments, and private sector decision makers to institutionalize the adoption of processes and practices and, 10) Identifying, sharing, and securing critical resources to sustain the work. The benefits of this project are improved statewide collaboration and improved urban rural Indigenous trust and interdependence resulting in a stronger regional food system across Arizona. The outcomes of this project will result in reimagined local food economic opportunities leading to the long term vision of a more vibrant, sustainable, and equitable community food system for all Arizonans. Intended beneficiaries include socially disadvantaged farmers and ranchers, local food producers, individuals experiencing nutrition insecurity, and institutions implementing food system programs and services. This grant will include subcontracts for food action plan implementation support with eight (8) Arizona based regional food coalitions including Flagstaff Foodlink, Verde Valley Food Policy Council, Yuma HEAL Coalition, Pima County Food Alliance, Ajo Center for Sustainable Agriculture, Maricopa County Food System Coalition, Coalition for Farmland Preservation and a Tribal Collaborative workgroup.
A10: 2022 | B10: AM22RFSPCA1060 | C10: The Regents of the University of California | D10: 990752 | E10: The California North Coast Emergency Food System Partnership seeks to build local regional emergency food systems that expand sales and mitigate risk for local food producers while reducing food insecurity. Over the past five years, Northern California has experienced catastrophic wildfires, landslides, persistent drought, the pandemic, and economic downturns, putting increasing pressure on local producers, the local regional food system, and emergency food aid. A coordinated emergency food system in this six county region Del Norte, Humboldt, Mendocino, Sonoma, Marin, and Napa County would expand markets for local producers while providing increased access to local, fresh, and healthy food for emergency food clients. Centering equity across all activities, the proposal mitigates geographic isolation, increases self sufficiency in times of emergency, and reduces disproportionate social, environmental, and economic impacts from emergencies and natural disasters fueled by climate change. The project encompasses chronic emergency food assistance (i.e. groceries) and crisis emergency food assistance (i.e. prepared meals at evacuation shelters provided during disasters). The project objectives are to (1) create additional market opportunities for local producers within emergency food supply chains to mitigate risk and maintain income during disasters (2) build collective capacity to improve emergency food systems by creating a strong network of partners, develop emergency feeding plans, and inventory local emergency food supply chain infrastructure and (3) identify recommendations to address policies, practices, and economic barriers to establishing effective local and regional emergency food supply chains. This effort will create additional markets for local food producers into emergency food supply chains to reduce risk of lost income and strengthen local and regional food systems. Deliverables include providing technical assistance and trainings to local food producers and creating sales opportunities by connecting them to emergency feeding agencies establishing a Network of Networks across the region assessing and inventorying food systems assets creating county and tribal emergency feeding plans developing policies, practices and economic recommendations that support emergency food systems and disseminating findings. Direct beneficiaries include local regional food producers, emergency food providers, BIPOC serving organizations, low income urban and rural communities, and Tribes. Across the region encompassing 12,545 square miles and a population just over 1.1 million communities of color and low income urban, rural, and tribal communities experience high rates of poverty and food insecurity and also experience disproportionate impacts from natural disasters, public health emergencies, and economic downturns. This work is significant because it will help local producers in these communities mitigate the risk of lost income from natural disasters, pandemics and economic downturns by providing additional emergency food market channels and it will support food security and expand community resilience. The project brings together a diverse set of partners including food producers, food policy councils, community based organizations, local and tribal governments, cooperative extension, and emergency planners to build upon shared experiences from responding to climate change induced natural disasters and the pandemic. Subaward partners will actively support the Partnership by guiding the Network of Networks, and leading Implementation Projects (Community Food Council for Del Norte and Tribal Lands, Humboldt Food Policy Council, and Petaluma Bounty). The Partnership formed in 2021 to bring together pre existing networks engaged in disaster relief and emergency food assistance in each of the six counties.
A11: 2022 | B11: AM22RFSPCO1045 | C11: Nourish Colorado | D11: 998757.5 | E11: The Collaborative Models among Rural Institutions and Standardizing Metrics for Local Purchasing (CMSM) Project aims to infuse more resources and cooperation among institutions, farmers, and food hubs so they can build their capacity and networks. The partnership will include Nourish Colorado, which will manage the overall project, the Colorado Departments of Education (CDE), Public Health AND Environment (CDPHE), and Human Services (CDHS), as the providers of publicly funded meal programs like K12 school lunches, early childhood education (ECE) meals, and Older Adult (OA) Meal Programs to assist us with developing relationships with institutional partners. We are partnering with Ogallala Commons to assist with strengthening partnerships with farmers and producers in southeastern Colorado, as well as Colorado State University (CSU) Food Systems Institute for Engagement to assist with engagement and evaluation. Each partner will have a role in each focus area. Additionally, the project will include one to two convenings of all partners every year of the project to discuss initial goals, data collection, and next steps. The goal of the CMSM Project is to develop baseline local procurement data and metrics and create and test a model for collaborative purchasing in southeastern Colorado. The CMSM Project will allow us to strengthen partnerships in the region, to provide more training and technical assistance support, agricultural producer support, evaluation support, and build the overall capacity of the program to promote farm to institution programs in southeast Colorado and build a model that can be replicated in other regions of Colorado.
A12: 2022 | B12: AM22RFSPDC1053 | C12: Dreaming Out Loud | D12: 999512.28 | E12: Our proposed implementation project, Scaling Cooperative Social Enterprise Expanding Market Access for Disadvantaged Farmers and Food Makers in the Washington, DC Region, offers creative solutions to barriers to market access faced by socially disadvantaged farmers and food entrepreneurs. As an expert provider of technical assistance and accelerator programming to food entrepreneurs and farmers, Dreaming Out Loud (DOL) will partner with DC Office of Planning s Food Policy Division (OP) and DC Central Kitchen (DCCK) to carry out the project. This is a particularly timely opportunity since in Summer 2022, DOL is set to expand by co locating its services in DCCK s new 36,000 square foot urban food hub and workforce development center. This facility will give DOL and DCCK the infrastructure to expand training, technical assistance, marketing activities, and direct sales opportunities through DOL and DCCK s social enterprise supply chains. This project will increase access to (1) food system infrastructure such as traditional and non traditional commercial kitchen space, refrigerated trucks, and cold storage through technical assistance and network development (2) qualified mentors and coaches 3) proven accelerator programs and workforce development services and 4) contracts offered by public institutions, federal and local nutrition programs, and other anchor institutions. Together, these efforts will improve marketing opportunities in our regional food system for socially disadvantaged participants by closing gaps in physical, social, and financial capital. The cross cutting networks of the project partners reflect decades of market building expertise and the unmatched visibility produced by their value chain building successes during the COVID 19 pandemic.
A13: 2022 | B13: AM22RFSPIA1062 | C13: Eat Greater Des Moines Email | D13: 946665 | E13: Eat Greater Des Moines, with the Iowa Food System Coalition, brings together the Regional Food System Working Group, existing Value Chain Coordinators (VCCs), the Iowa Farmers Union, Iowa State University Small Farm Program, and the Food Hub Managers Working Group in support of value chain coordinator expansion. The Regional Value Chain Coordination for a Stronger Iowa Food System project will create two new regional value chain coordinator positions, support three current value chain coordinators, and a central coordinator. Five regions across Iowa, including two critical geographic voids, will be supported to connect farmers, producers, purchasers and resources. The central coordinator will help the VCCs improve processes, share examples of leveraged infrastructure developments and collaborate on policy recommendations. Including VCC impact assessment with education and policy development is essential to support the sustainability of the relationship infrastructure. VCCs enable producers and buyers to improve their competitive position leading to more profitability and viability. VCCs can engage retailers and institutional purchasers to lead them through the process of local purchasing and connect them with food hubs, thus reducing costs and navigating hurdles for them. Having consistent local buyers will reduce risk for farmers, create more demand for local food, and enable local producers and food businesses to scale up production with confidence and sustainability. This is especially true in rural regions. This project benefits both producers and buyers in the five regions identified. The project included subrecipients such as University of Northern Iowa to perform project evaluation and VCC impact analysis, partial funding to existing VCCs at Iowa State University Extension and Healthy Harvest, the Iowa Farmers Union to engage in statewide advocacy for project outcomes, and StoryStruck Marketing to develop dissemination tools and a website for the project.
... A56: 2024 | B56: RFSP24000595 | C56: Southeast Regional Cooperative, Inc. | D56: 250000 | E56: The Boundless Distribution Systems Development Partnership will bring together the Southeast Regional Cooperative (SERC) and a diverse community of partners including Feeding America, Partner State Associations, Georgia Department of Agriculture, Georgia State University, and the Southeast Produce Council with a goal of increasing efficiencies throughout the supply chain that support the charitable food network. SERC will plan and develop strategies in critical areas including transportation management, middle supply chain logistics, value added processing and integrated data management, culminating in a project plan for a regional service center. For profit organizations and institutes of higher education will be engaged to conduct research, integrate diverse data platforms and operating systems, and optimize planning for sourcing and distribution. Partners will plan and design a regional service center offering freight supplier development and management, freight brokerage, weekend and evening support, and billing services, including programmatic grant administration. SERC will engage a wide range of community partners including growers, producers, partner organizations and our neighbors to explore and analyze scope of work, location, value added processing, aggregation, distribution, and 3PL partnerships. Attention will be given to socially disadvantaged entities to create sustainable markets, while developing capacity to secure funding for long term stability. Twelve convenings will be conducted over two years. Two convenings will be for the partnership leaders, and ten will be held specifically for 1) freight and logistics, 2) middle supply chain, 3) engaged data/IT organizations, and 4) growers and other agricultural producers partnerships, and food banks and other engaged non-profit organizations.

Sheet OMDG
A1: Legal Name | B1: City | C1: State | D1: Zip 5 | E1: Congressional District | F1: Amount Requested | G1: Project Type | H1: Project Title | I1: Project Summary
A2: Venture Milk LLC | B2: Slocomb | C2: AL | D2: 36375 | E2: 2 | F2: 950000 | G2: Processing Capacity Expansion | H2: Expanding Deep South Organic Dairy Processing Capacity | I2: This project increases output and lowers the costs of a small organic dairy processing plant serving underserved producers in economically distressed areas. By supporting a full-time sales position, it expands market access both for existing organic dairy producers and for dairy producers transitioning to organic. It does this through co-packing, two processor-affiliated brands, and other marketing channels it has developed and will continue to expand. Plant upgrades include adding packaging options optimized for food service and food product manufacturers that represent over a third of the national demand for dairy products. The desire central outcome of these activities is to develop product market matches that successfully generate sustained income for organic dairy producers by meeting the needs of existing sales outlets more efficiently and completely.
A3: Agoge Life Inc. | B3: Phoenix | C3: AZ | D3: 85044 | E3: 4 | F3: 2054000 | G3: Market Development and Promotion | H3: Organic Hemp Protein Isolate - Market Development & Expansion Effort | I3: Agoge, a sustainable organic product-focused company, has spent 2 years and significant funds researching developing a foundational set of products with organic ingredients to support improved health outcomes. The ingredients in its products are isolated hempseed proteins, certified Organic by the USDA. In short, Agoge is introducing the USA’s first Organic Hemp Protein Isolate (OHPI). The project aims to open the OHPI market and drive the expansion of the upstream (supply) and downstream (demand) supply chain for this organic, sustainable rotational crop through education, marketing, and consumer buyer outreach. The objectives include: 1) Opening the OHPI market by providing the food ingredient sector with the USA’s very first Organic Hemp Protein Isolate products a deeply researched foundational ingredient and its first 3 formulated finished goods. 2) Targeting and educating 8,000 consumers a month using traditional and digital marketing campaigns through education events targeting dietitians, nutritionists, doctors, etc., and 3) Hosting a 20x20 exhibitor booth at 10 of the USA’s biggest ingredient and food conferences. The project will include OHPI industry connector events twice a year for 2 years across 4 different cities.
A4: Craig Schmitt | B4: PEORIA | C4: AZ | D4: 85383 | E4: 8 | F4: 98283 | G4: Simplified Equipment | H4: Expand Organic Grain Processing for NE Montana | I4: The Schmitt’s Farm converted to 100% organic in 2018. The farm grows spring wheat, hulless oats, lentils, yellow peas, chickpeas, hemp grain, canola, alfalfa, and flax. It has a crop rotation of 25% cereal grains (wheat, oats, etc), 25% Legume (peas, chickpeas, alfalfa), 25% oil seeds (flax, hemp seed, canola) and 25 % fallow with cover crop. A number of innovative practices are being tested continuously to get closer to notill or minimum tilling using cover crops, interseeding multiple crops together and relay seeding crops together. The purpose of this project is to help address a current bottleneck in the organic marketplace: which is a lack of organic grain processing infrastructure. Goals include: 1) strengthening and expanding farm capacity 2) Providing grain cleaning services to other organic growers, and 3) increasing access to organic grains. The purchase of this equipment will allow Schmitt’s Farm to increase its annual gross income, increase storage capacity by 13,500 bushels, decrease annual miles traveled by 60,000 miles per year, and increase processing capacity of organic grains by 800,000 bushels per year. The main equipment beneficiaries will include Schmitt Organic Farms and other farms in the region that will now have local or more regionalized access to organic grain processing. This will have a trickle-down effect leading to greater access to organic grain throughout the entire North west region. This will also positively impact buyers as 3 Schmitt’s Farm will be able to more reliably provide them with products. In turn, consumers, bakeries, and restaurants will also have greater access to organic grains.
A5: Rumiano Cheese Company | B5: Willows | C5: CA | D5: 95988 | E5: 1 | F5: 3000000 | G5: Processing Capacity Expansion | H5: Expanding Market Opportunities for Organic Dairy Producers in Northern California Through Value-Added Processing and Marketing | I5: Dairy is the largest organic commodity in the United States, with 1.6 billion in annual sales, yet organic milk represents just 2 % of the nations dairy production and is declining. USDA’s Organic Dairy Market News reports that year-to-date sales of organic milk products are down 1.6 % from the prior year. As organic dairy production costs have increased in recent years, the price premium of fluid organic milk over conventional milk has eroded, leaving organic dairy producers, most of them small family farms, with shrinking on-farm profits that threaten their livelihood. To address this challenging issue, Rumiano Cheese Company, seeks to expand in-house processing capacity to make and market innovative, high-demand organic dairy products in channels that offer a higher price premium over fluid. Activities to be performed will include 1) installing a state-of-the-art processing line to upcycle organic cheese trim into value-added sauces, dips and spreads; 2) acquiring additional equipment to create artisanal specialty cheese wheels inhouse; and 3) expanding marketing, sales, and innovation to gain retail access and build consumer demand for the expanded volume produced through this project. This venture’s goals are to process an additional 32,372,700 pounds of fluid milk and cheese trim, generating approximately $31.5 million in sales revenue and benefiting 27 Northern California pasture-based organic dairy producers during the project period.
A6: Heal the Earth | B6: Cardiff by the Sea | C6: CA | D6: 92007 | E6: 9 | F6: 2473795 | G6: Processing Capacity Expansion | H6: Improving the Viability of the Domestic Organic Avocado Market | I6: Heal the Earth at Wild Acres Farm, a San Diego County nonprofit and avocado farm, will improve and grow the long-term viability of the domestic organic avocado market by coordinating a direct to consumer valuechain and launching a comprehensive regional marketing campaign. This project will facilitate the flow of avocados into regional markets by leveraging the expertise of, and building on the work done in partnership with, the Avocado Growers of California, the City of Escondido, and other stakeholders. Collaborative efforts will include marketing and outreach to buyers and consumers, promoting opportunities to sell and buy US-grown avocados at a local food hub, a feasibility study, and resulting strategic promotional efforts tailored to the needs of domestic organic avocado growers and US consumers. Heal the Earth will expand staff capacity, build and maintain relationships with certified organic growers, establish new and expanded markets for organic avocados, and develop and execute a marketing plan that differentiates the organic, US-grown product to both buyers and end consumers. Heal the Earth will 1) build relationships between organic avocado producers and consumers, 2) create alternative market channels for organic avocados and ancillary organic farm products, 3) increase consumer awareness of the benefits of locally-grown, 7 California-produced avocados. There is a growing demand for avocados, and organic fruit both supports local farmers and climate-smart growing practices.
A7: TIDAL FOODS, INC. | B7: SAN FRANCISCO | C7: CA | D7: 94107 | E7: 11 | F7: 660970.21 | G7: Processing Capacity Expansion | H7: Unlocking Sustainable Ocean Farming: Processing and Product Manufacturing Expansion for US-grown Organic Kelp | I7: This project paves the way to making regenerative kelp farming a viable industry for rural seaside farming communities that rely on volatile wild-caught seafood. Historically, kelp farming within the US has not been considered a lucrative industry because of perceived competition from Asian markets and a lack of profitable end markets for US-grown kelp products. As a result, 95% of seaweed products sold in the US are imported from Asia. Consumers are already proving they are ready for kelp-based snacks, so now is the time to invest in scaling up the kelp industry, spurring demand for more kelp farmers to grow a regenerative and ocean-friendly crop. The major limitation for kelp farmers is a lack of processing and product manufacturing capacity to transform kelp into high-value products. By providing a profitable end market for kelp 12 Tides solves this issue. This project scales up the production of a highly sought-after product line that provides high quality, consistent revenue to rural kelp farmers. Kelp is easy to grow, produces low CO2-equivalent emissions than corn, and can be reliably harvested year after year while mitigating ocean acidification and increasing marine biodiversity. This provides economic stability for farmers in communities historically reliant on increasingly volatile seafood industries as well as a healthy snack product for consumers. This grant allows 12 Tides to scale its processing capacity, support a nationwide launch, and expand the supply chain by purchasing from 27 new organic farms, while employing 144 staff, and supporting 275 kelp farming jobs in the U.S.
A8: ZEGO LLC | B8: San Francisco | C8: CA | D8: 94117 | E8: 11 | F8: 3000000 | G8: Processing Capacity Expansion | H8: Collaboration for Sustainable Growth: Advancing the Organic Gluten-Free Grain Value Chain, expanding processing capacity, product access and awareness, and building consumer trust in organic food | I8: ZEGO is a woman-owned B Corp-certified brand focusing on supply-chain transparency and purity testing using Montana Gluten Free’s hull-less, high-protein, organic oats. ZEGO sells products in 1500+ stores nationwide. The project will increase processing and consumption of organic, gluten-free, high-protein oats and rotational crop millet in Montana and the surrounding growing region by creating a collaborative integrated value chain (CVIC). The goals are to 1) expand organic processing capacity at Montana Gluten Free (MGF) to alleviate a regional grain processing bottleneck that forces farmers to sell premium crops for bird and animal feed at 50% of full value; 2) develop more products from organic specialty grains for people with medically restricted diets due to allergies or gluten intolerance, toxin and pesticide concerns, or diabetes or to increase dietary plant protein; 3) increase special-diet consumer pull (demand) of organic grains by expanding product trials, adding sales channels, building consumer trust in organic food; and 4) benefit the environment by decreasing transportation miles and promotion of hulless oats, which produce 50% less carbon emissions, and drought-tolerant millet, which uses 1/3rd less water than other grains. In addition to the project goals Zego predicts that the project will 1) increase organic finished goods capacity 5 by integrating operations at MGF with faster and more efficient equipment for bag filling and improved processing efficiency; 2) upgrade food safety certification level; 3) establish a millet value chain by purchasing and installing equipment to dehull millet. It will also help setting up procurement contracts with regional farmer and developing 3-5 new organic specialty grain products, in collaboration with Snacktivist, targeting markets such as food service accounts and big box stores, and build B2B ingredient sales. The project will allow for the implementation of marketing strategies led by a specialized marketing director to increase awareness and adoption of organic specialty grains among special-diet and non-toxic living consumers; and collaborate with technology partner Food Vision to enhance ZEGO’s purity transparency system, making product information accessible and expanding the scope of information to include links to farmers.
A9: Wehah Farm, Inc dba Lundberg Family Farms | B9: Richvale | C9: CA | D9: 95974 | E9: 1 | F9: 3000000 | G9: Processing Capacity Expansion | H9: Expanding the United States organic rice market by investing in production, processing, and marketing infrastructure | I9: In 2022, US farmers produced more than 16 billion pounds of rice to serve domestic and international consumers (USDA Economic Research Service). Still, less than 1% of the rice produced in the United States is organic, despite strong and consistent growth in US demand for organic food. With more than 82% of US households buying organic products regularly, the Organic Center notes demand in the US for organic rice exceeds domestic supply, encouraging significant competition from imports. In fact, US imports of rice have steadily increased over the past five years, growing more than 36% from the 2017/2018 crop year to the 2021/2022 crop year. This is primarily due to the major barriers that exist to producing, processing, and marketing organic rice, namely higher costs of production, and lack of processing and marketing infrastructure. To meet current US consumer demand and expand opportunities to build the US organic rice 8 market (project purpose), Lundberg Family Farms, the nation’s largest organic rice producer and processor, will launch a comprehensive effort to support current and transitioning organic producers in increasing organic rice production. Project activities toward removing barriers to entry for producers include grower outreach and technology adaptation expanding processing capacity to create more and better markets for organic producers and executing marketing and promotional activities that will help to build commercial markets for US organic rice products. This project’s goals (deliverables and expected outcomes) include achieving 3,000 new acres of organic rice processing and a $17 million increase in domestic regenerative organic rice sales by the end of the project period.
A10: Vista Livestock Co. dba Burroughs Family Orchards | B10: Denair | C10: CA | D10: 95316 | E10: 10 | F10: 1166250 | G10: Market Development and Promotion | H10: Sustainable Growth Through Enhanced Market Reach and Product Innovation | I10: Burroughs Family Orchards (BFO) is a certified organic and regenerative family farm committed to fostering a sustainable food system. This project is designed to increase consumption of BFO's organic almond and olive products, drive market interest, and meet the growing demand for high-quality organic products. BFO plans to broaden its market reach by expanding into new geographic regions, specifically in the Central and Southern U.S. territories. This strategic expansion will be facilitated through hiring a marketing contractor and a broker, who will work to increase the visibility and availability of BFO's organic almond and olive products. Additionally, BFO will invest in developing new and improved organic products, partnering with experienced consultants to expand their product range and drive market interest and demand for organic products. To meet the growing demand for organic almonds, BFO plans to enhance its storage and distribution capacity by investing in temperature and weatherproofing its existing warehouse storage space to ensure optimal freshness and shelf life of their products year-round. These enhancements will enable BFO to scale its operations in tandem with the rising demand for organic almonds. The project is expected to significantly improve BFO's ability to compete in the organic sector. It will advance their mission of promoting a sustainable food system, contributing to the growth of the organic market, and delivering high-quality, innovative almond and olive products to consumers across the nation.
A11: Rock Front Ranch LLC | B11: Santa Maria | C11: CA | D11: 93456 | E11: 24 | F11: 89180 | G11: Simplified Equipment | H11: Organic marketing expansion of fruit business into Northern California | I11: The Rock Front Ranch’s (RFR) project goal is to increase market access to organic products by improving the efficiency of transporting organic fruit to organic minded consumers and generating employment opportunities in a community with persistent poverty. Rock Front Ranch (RFR) has provided organic jujube fruit to 29 Whole Foods in Southern California since 2017. Recently, the ranch has endeavored to serve Whole Foods and other organic stores in the Northern California region. Those efforts have been curtailed by lack of sufficient transportation capabilities and the prohibitive expense of contracting for 3rd party delivery. The addition of two delivery trailers would allow RFR to provide both fresh and dried organic jujube fruit to the entire network of Whole Foods in Northern California, an additional 39 stores, as well as other organic stores. Two trailers will provide the capacity to deliver fresh and dried organic jujube fruit to both Northern and Southern California markets simultaneously, increasing efficiency as well as creating two 4 to-four new employment opportunities for residents of the Cuyama Valley, a community with persistent poverty.
A12: California Craft Maltings, LLC dba Admiral Maltings | B12: Alameda | C12: CA | D12: 94501 | E12: 12 | F12: 99033 | G12: Simplified Equipment | H12: Grain Milling Equipment to Produce Organic Milled Grains and Organic Sprouted Grain Flours | I12: The purpose of this project is to purchase and install milling equipment to allow for new product offerings and expanded organic capacity for milled raw grains. It is a natural extension of what Admiral Maltings already does to mill and package organic flour for bakeries and grist (raw grains) for distillers. Milling organic flour for bakers and distillers’ grist uses similar agricultural ingredients to what California Craft Maltings already sources. But it is a different process from malting organic grain and requires new equipment. This equipment purchase will allow Admiral Maltings to increase the contracted acreage of organically grown grain, increase land under organic certification, and create a more resilient, local agricultural economy to supply bakers and distillers. It will lead to aggregate efficiencies for growing, storing, and processing organic grains. There is increased consumer demand to know who grows their food, where it is grown, where it is processed, and who mills it.
A13: CALIFORNIA CERTIFIED ORGANIC FARMERS INC | B13: Santa Cruz | C13: CA | D13: 95060 | E13: 19 | F13: 3000000 | G13: Market Development and Promotion | H13: Marketing to Expand Economic Opportunity for Small and Underserved Farmers | I13: California Certified Organic Farmers (CCOF), Inc. has over fifty years of experience working with organic producers and is now the largest member-based organic agriculture organization in California, and owns the largest organic certification company in the U.S. The purpose of this grant is to improve and expand market access for small and underserved organic farmers. The three goals for this grant are: 1) to address two key obstacles restricting growth in organic sales: which are the lack of consumer clarity on what “organic” means and a perceived lack of consumer confidence in the seal; 2) to create market paths for small and underserved organic producers by linking them with buyers actively looking to source their products; and 3) to educate and provide farmers with tools to talk to consumers and buyers about organic. These goals will be achieved by launching a multi-channel marketing campaign, creating a marketing toolkit, marketing trainings for farmers, and updating and disseminating an organic sourcing directory to school and retail buyers. The expected outcomes of this project are that consumers and buyers will gain knowledge about organic products and that small and underserved producers will increase organic production to meet the increased demand through direct-market channels and buyer business transactions.
... A15: ECOCENTER INC | B15: San Juan Capistrano | C15: CA | D15: 92675 | E15: 49 | F15: 2975397 | G15: Processing Capacity Expansion | H15: Processing Capacity and Distribution Expansion for Value-Added Products | I15: Despite having a high density of small farms, Southern California significantly lacks certified organic processing facilities, an issue that negatively affects small and underserved farms that rely on timeconsuming, costly hand labor to process and add value to their organic commodities. To address this 9 bottleneck, The Ecology Center (TEC) proposes to expand its processing and distribution capacity for valueadded products (VAP) made from organic corn, legumes, and fruit, by providing a shared processing service to facilitate market access for small organic farms. Project activities include 1) renovating its processing warehouse to accommodate new equipment for high-demand VAP including jams, tortillas, dried beans, and sauces, 2) expanding partnerships to benefit at least 15 organic farms, and 3) expanding TEC’s current DTC sales model that reaches 70,000 consumers to larger channels, by leveraging partners’ channels and relationships with regional groceries. This project will increase processing by 80,000 lbs. of organic corn, legumes, and fruit processed into 372,000 units of organic VAP. It will reach at least 40,000 more repeat consumers, influencing up to 400,000 new consumers by the addition of 10 or more sales channels. This project will facilitate market access for 15 or more Southern Californian organic producers (at least 10 of which are small, beginner, or underserved farms). It will also increase their profitability with access to processing equipment and increase consumption of locally made organic products–inducing approximately $2.2 million in sales by the project’s third year.
A16: Turning Green | B16: Sausalito | C16: CA | D16: 94965 | E16: All | F16: 355808 | G16: Market Development and Promotion | H16: Growing Organics through Local School Procurement | I16: Turning Green continues integrating local, organic food into California’s K-12 school meal programs. This project will leverage the massive purchasing scale of the school food sector to grow the organic supply chain by bringing together school food networks, small disadvantaged organic farmers, and local agricultural support organizations. The project will provide added training and technical support to school food service teams and organic farmers to align planning, implementation, logistics, and metrics to grow the sale of organic products to schools in California. Given that much of the current food purchased and served in schools is not organic, this segment is an attractive and burgeoning opportunity to expand the organic marketplace. Turning Green has facilitated and supported procurement and has served fresh, local, organic, nutritious food in K-12 schools. In 2020/21, during the pandemic, they worked with a local school district of 28,000 students to transition its entire meal program to 100% organic with 41 new vendors, resulting in over $17 million that flowed into the organic supply chain. Since then, Turning Green has partnered with seven more school districts to spur demand and enlist support from many small organic farmers to grow supply. Working with producers and school districts, Turning Green identifies gaps and market barriers while creating innovative systemic solutions for crop planning, delivering, and consuming high-quality goods. An experienced team is equipped to expand their work in building the organic market with school food programs. Leveraging local agricultural support organizations and school food networks, the project will provide added training and technical support to school food service teams and small disadvantaged farmers to align planning, implementation, logistics, and metrics to meet school requirements.
A17: Feirreria & Son Dairy | B17: Arcata | C17: CA | D17: 95521 | E17: 2 | F17: 99811.5 | G17: Simplified Equipment | H17: Purchase of Equipment for Organic Dairy Business and Local Organic Market Expansion | I17: Ferreira & Son Dairy has been certified organic since 2007 and became certified grass fed in 2016. Historic drought and increasing feed costs in recent years have forced local dairies to make decisions about the future of their generational businesses. In response to these industry and climate -based challenges, Ferreira & Son Dairy has embarked on a five-year plan to remain self-sufficient by expanding and diversifying production, taking over their own distribution thereby cutting the costs of middle distributors. During the first year, 2021-2022, Ferriera & Son Dairy completed the first phase of this expansion, building Humboldt County’s first truly local milk processing and bottling plant. The milk is processed right from the tank, bottled into glass bottles, then distributed directly to local stores. The next phase of the project is the 11 acquisition of equipment to expand production. The funds from this opportunity will enable the dairy to purchase equipment that will quadruple production from 300 to 2000 gallons per week of milk with diversified fats percentages that can be used to develop, produce and distribute other products that will generate more income for the dairy and increase growth of the market for organic products overall in the local economy.
A18: Alexandre Dairy | B18: Crescent City | C18: CA | D18: 95531 | E18: 24 | F18: 3000000 | G18: Processing Capacity Expansion | H18: Organic Market Development Grants - 2023 | I18: Alexandre Dairy (the “Dairy”), is the 1st Certified “Regenerative” US organic dairy, producing 100% A2/A2, grass-based milk, and organic hay and silage, is seeking funding to replace antiquated milk collection, cooling, and storage equipment and to purchase post-harvest hay collection equipment to increase domestic supply chain capacity and facilitate expanded market development. As a vertically integrated company, the Dairy supplies organic milk to Alexandre Family Creamery (“AFC”) for processing into Alexandre Family Farm (“AFF”) branded, as well as co-packaged, products. Nationwide demand for organic, A2/A2 grass-based, certified regenerative milk has significantly increased but the outdated raw dairy milk collection equipment cannot keep up with weekly demand and projected brand growth, and the Dairy’s ailing harvest equipment curtails its ability to collect and store feeds within a short harvest season. The Dairy currently produces 55% of its organic livestock forage annually and can increase production by 10- 15% simply by upgrading equipment, helping to reduce regional pressure on organic livestock forages. Investment in new equipment supporting milk collection/storage, post-harvest hay/silage processing, and transport to provide on-farm resiliency, will support the Dairy’s investment in national market penetration of its organic farm-gate products. The project would benefit Pavel’s Yogurt Company and Kefir Lab, which AFC co-packs for and the Farm sells organic raw dairy, Rumiano Cheese, which the Dairy supplies with 25% of its weekly organic milk volume, and Humboldt Creamery which also uses 22% of the Dairy’s production to make organic fluid milk, ice cream and milk powder. In addition, the West Coast’s organic, pasture based dairy producers which support 85% of California’s organic fluid production will benefit from the Dairy’s brand penetration into new and expanded regions educating consumers about the importance of California climate friendly milk, innovative on farm certifications that add margin, and models for small organic family farm expansion and innovation focused on genetics, grass-fed and flash grazing practices.
A19: Tuxedo Corn Co, LLC | B19: Olathe | C19: CO | D19: 81425 | E19: 3 | F19: 623545 | G19: Processing Capacity Expansion | H19: Colorado Organic Dry Beans- Processing Capacity Expansion | I19: The project proposes a planning and implementation process for the development of a permanent certified organic, dry bean processing facility located in Olathe, Colorado. The facility will provide a certified organic process for the cleaning of dry beans received directly from field harvesting and enable versatile packaging of dry beans. The planning process will consist of completing Technical and Economic Feasibility analyses and Marketing and Business Plans for such a facility. The first goal is to optimize the technical aspects of processing to ensure efficiency and increase capacity in a certified organic dry bean cleaning and packaging facility. This will provide a finished product, packaged in various weights, which accommodate market needs and consumer demand. The project will develop a Marketing and Business plan to optimize economic benefits and purchase of equipment to implement a facility. Project is expected to improve access for producers in the Western Slope to sell products into regional and national organic dry bean markets, provide incentives to expand the volume and varieties of organic dry beans grown in these regions, and increase regional organic dry bean sourcing accessibility for buyers and consumers.
A20: Honey Rock LLC | B20: Delta | C20: CO | D20: 81416 | E20: 3 | F20: 99597 | G20: Simplified Equipment | H20: Local Communities Celebrating Colorado's Peaches Year-Round | I20: In 2022, a farm partner company received a grant to purchase equipment to turn organic peaches into puree that could be used in food service and production of beverages and value-added foods. The goal was 12 to make Colorado’s celebrated peaches available year-round. An additional goal was to upcycle waste peaches. Tons of peaches go to waste each year because of minor imperfections or because they are too ripe to travel through traditional distribution channels. This summer, that company began puree production for restaurants, breweries, and other food producers. This project includes two goals; 1) to market this local resource year-round in ways that honor the goodness and flavor of the fruit and 2) to celebrate this local resource within the community, in ways that can nourish ALL community members. One solution is to package the puree in squeeze popsicles that are shelf-stable, to be frozen on-demand. The joy of a squeeze popsicle is a true celebration of local flavors. The plan is to keep the fruit content near 100 percent. This means that these organic popsicles will be healthful for everyone. This equipment grant will allow Honey Rock to purchase a popsicle machine, and supporting equipment, to make delicious, safely-produced servings of fruit. This will help keep costs down and make these items affordable for distribution to community schools, hospitals, and the food bank. This product is in line with the farm’s initiatives to reduce food waste by upcycling peaches to 1) adopt the most earth-friendly practices, 2) level the farm’s working hours by adding off-season work to solve local production and storage problems that keep local institutions from serving more local fruit, and 3) bring greater awareness to and appreciation of local agricultural resources.
A21: Colorado Grain Chain | B21: Denver | C21: CO | D21: 80212 | E21: 1 | F21: 269270 | G21: Market Development and Promotion | H21: Growing & Connecting Colorado’s Organic Grain Economy: Enhancing Organic Grain Market Opportunities for Producers, Processors, and Value-Added Product Makers | I21: By working with several high-influence partners in the organic food space, the Colorado Grain Chain (CGC) will enhance market opportunities for producers, processors, and value-added product makers of organic grain for human consumption. Although grains make up an average of 30-50% of dietary intake, the organic grain market for human consumption is relatively limited, with little emphasis on local sourcing. Since the inception of the Colorado Grain Chain in 2019, the non-profit organization's mission has been to grow and connect a community-centered grain economy in the state of Colorado. This work involves connecting the membership base of 50+ Business and Consumer Members to educational and marketing resources, partners, and technical assistance. CGC’s membership base ranges from farmers, processors (millers and maltsters), to artisanal makers (bakers, brewers, distillers, chefs), food hubs, and institutions. The Organic Market Development Grant (OMDG) will allow Colorado Grain Chain to support stakeholders in the grain supply chain through the promotion of organic grains in value-added marketplaces in alignment with the Colorado Grown Grains marketing initiative, while building off and expanding current program models to organic grains. Specifically, the project seeks to support connections through the grain supply chain that a) incentivize the cultivation of diverse organic grains through Microgrants for small businesses/farms, b) enhance distribution of organic grains through increased visibility in value-added market channels, and c) increase market awareness and demand for locally sourced, food-grade, organic grain through event coordination and the continuation of the Colorado Grown Grains co-brand strategy.
A22: Hobbs & Meyer, LLC | B22: Cortez | C22: CO | D22: 81321 | E22: 3 | F22: 100000 | G22: Simplified Equipment | H22: Increasing processing capacity and market share for certified organic drought and heat tolerant grains and legumes for food, feed and cover crops | I22: Hobbs Meyer, LLC DBA Pueblo Seed Food Co (Pueblo Seed) is a family farm located in Southwestern Colorado. The farm has been certified organic since 2001 by the Colorado Department of Agriculture and specializes in open pollinated vegetable seeds, varietal garlic, and heritage grains and legumes on 30 acres. This project will allow Pueblo Seed to purchase equipment to increase capacity in its facility to scale up processing and develop new products from these crops for seed feed and food markets. During the COVID19 pandemic, the farm began producing a line of 7 value-added grain products and working towards opening a seed and bakehouse. In 2021, the farm purchased a 5300-square foot commercial building in downtown Cortez. In 2022-2023, the farm purchased a food grade seed cleaning line and other grain processing equipment for making products and providing seed cleaning services to partner growers. During 2023, the farm increased the seed of 10 species of drought and heat tolerant grains and legumes. Organic drought hardy heritage grains and cover crops, in particular, are in extremely short supply in the U.S. (Hubbard et al., 2022). Pueblo Seed’s goal is to become a central organic supplier of cowpeas, tepary beans, finger millets, pearl millets, amaranths, grain sorghums, culinary ryes, culinary barleys, select wheat, and flour maize. The business will utilize its existing seed customer list and long-term relationships with national seed companies to increase the seed market and work through food hubs, food pantries, and institutions to increase food market share.
A23: Connecticut Department of Agriculture | B23: Hartford | C23: CT | D23: 6103 | E23: 1 | F23: 263743 | G23: Market Development and Promotion | H23: Increasing Market Access for CT Organic Producers and Handlers | I23: Consumer awareness about Connecticut’s certified organic producers and handlers is largely unknown. The Connecticut Department of Agriculture will use these grant funds to increase market access for certified organic producers, producers transitioning to organic farming, and certified organic handlers in Connecticut by coordinating with Transition to Organic Partnership (TOPP) partners, including the University of Connecticut (UConn) Extension and the Connecticut Northeast Organic Farming Association (CT NOFA). The goal of this project is to strengthen new and emerging markets, strengthen farm to institution market channels, increase producer and handler knowledge and skills to market their organic products, and foster consumer education to increase demand for organic products. Proposed goals will be accomplished by 1) evaluating the current market for CT Grown organic products in CT to understand consumers’ perceptions and understanding and to evaluate areas for growth and improved market access; 2) examining 14 opportunities for CT Grown organic product sales specifically for farm-to-institution; 3) implementing new communication strategies to reach consumers in the state to increase awareness and highlight CT Grown organic products and producers (which considers the information gained through the market evaluation), and 4) developing and conducting a workshop series for transitioning and certified organic producers and handlers to implement new marketing strategies and capitalize on areas for improvement identified by the results of marketing research.
A24: Latino Farmers Association | B24: Washington | C24: DC | D24: 20015 | E24: 1 | F24: 2738467.4 | G24: Processing Capacity Expansion | H24: Expansion of organic markets, aggregation and distribution for underserved producers and consumers in the greater District of Columbia, Maryland and Virginia area. | I24: The Latino Farmers Association’s (LFA) project aims to foster equitable participation in the organic marketplace for historically underserved and socially disadvantaged farmers and ranchers, veterans, and beginning farmers, with a concerted effort to combat food deserts in the District of Columbia, Maryland, and Virginia. To do so, LFA will pursue four key objectives. First, LFA will expand the organic vendor capacity of the Van Ness Farmers Market, in the District of Columbia, by facilitating a transition to an exclusively organic market and obtaining organic certifications for vendors via partnerships with the Transition to Organic Partnership Program (TOPP) Regional Lead, Pennsylvania Certified Organic, and the Organic Trade Association. Second, LFA will open three new organic farmers markets in healthy food priority areas in the District of Columbia and one in Southwest Virginia. Third, the association will develop a scalable Community Supported Agriculture (CSA) producer-to-consumer system supported by a Virtual Marketplace, which will connect market vendors with individual and institutional consumers. LFA will develop a diversified marketing strategy to build robust relationships with institutional buyers, distributors, grocery stores, and food co-ops. Finally, LFA will enhance market accessibility for producers by acquiring one box truck, one mobile market, and one delivery van. This will enable LFA to increase the scale and variety of product offerings that are now limited by transport and storage constraints. By providing an enhanced distribution process that reduces the cost of transport to market and includes eggs, meat, dairy and value-added products, LFA will diversify the producers’ income streams and cash flow, while lowering the collective carbon footprint.
A25: LS Wholesale LLC | B25: Washington | C25: DC | D25: 20036 | E25: 1 | F25: 2170610 | G25: Processing Capacity Expansion | H25: Opening up New Markets for Organic Chickpeas via Safe Quality Food Certified Hummus | I25: Little Sesame will expand the domestic certified organic chickpea market by increasing aggregation, processing, and distribution of its consumer-packaged line of hummus while simultaneously growing consumer demand through enhanced sales and marketing capacity. Over the past several years, droughts, flooding, and war in top chickpea-producing countries have led to an increased market demand for domestically grown chickpeas. That, paired with a growing interest in plant-based foods that rely on chickpeas and other legumes, creates a unique opportunity for organic chickpea producers in the United States. Yet, the market remains underdeveloped. Northern Plains farmers in the U.S. have difficulty finding direct sales relationships for chickpeas, a crop abundantly grown in rotation with wheat due to its soilbuilding properties. By achieving SQF certification, investing in manufacturing improvements, and implementing a shopper, trade, and field marketing program, Little Sesame will leverage market demand and create a much-needed direct market for 10 domestic chickpea farmers, purchasing 800,000 pounds of chickpeas annually across 2,000 production acres. Marketing efforts targeted at distributors, retailers, grocery stores, and household consumers will highlight the value of choosing products sourced from domestically grown certified organic chickpea growers and bring increased opportunities for certified organic producers for years to come.
A26: Organic Trade Assoication | B26: Washington | C26: DC | D26: 20001 | E26: 1 | F26: 2220372 | G26: Market Development and Promotion | H26: Growing organic markets through consumer education and promotion | I26: The project will stimulate the demand for and increase the sales of organic products by promoting the science-backed benefits of USDA certified organic products and farming to consumers. Organic is an umbrella term that addresses several individual product claims; however, consumers remain confused about the wholistic requirements of the USDA organic label and how they translate to benefits for people and the planet. By providing consumers with access to more credible information about what organic production and processing means and the benefits it provides, consumption of organic will increase. This joint project by The Organic Center and the Organic Trade Association (OTA owns the TOC) will be done in collaboration with Organic Voices and an Industry Advisory Committee (including TOPP regional leads) to develop fresh creative content on the regulatory and science-based environmental, animal, and human benefits of organic. Targeted content that motivates consumers to purchase pinpointed products like organic dairy, grain, and fiber will be prioritized. The creative content will be promoted through a full-scale integrated marketing campaign leveraging TOC and Organic Voices' existing consumer networks and paid advertising. Targeted efforts will ensure that promotion reaches beyond the mainstream organic markets into regions and communities where organic production is not already thriving. The Industry Advisory Committee will include partners from underserved communities and pinpointed markets to ensure the 16 creative and promotional campaign meets industry needs and expectations. The project will culminate by sharing learnings and successes in the creation of effective organic consumer marketing strategies, content, and messaging with the organic industry at large to increase their return on investment for future marketing opportunities. Printed copies of the final report will be disseminated to all addresses listed in the Organic Integrity Database (approximately 27,400 addresses), which includes around 19,000 producers (livestock and crop scopes) and 8,400 buyers (handler scopes).
A27: New Universe Food | B27: LIVE OAK | C27: FL | D27: 32060 | E27: 3 | F27: 97804.42 | G27: Simplified Equipment | H27: Refrigerated Van for Shipping Organic Products | I27: New Universe Food, LLC is a small business committed to promoting a healthier lifestyle by selling organic products. This grant will allow New Universe Food to purchase a much-needed refrigerated delivery van, allowing fulfillment of the promise to deliver fresh, high-quality organic products to a larger customer base along with supplying underserved communities who lack access to healthy, organic food. This van will further help them source organic produce from local and out of state organic growers and vendors that they can process as well as deliver to markets. The purpose of acquiring a refrigerated van allows New Universe Food to fulfill the promise of delivering fresh, high-quality organic products, and will also enable to reach a larger customer base. The company will be able to expand market reach and promote organic products by traveling to (and serving at) farmers markets, a range of food expos, community bazaars and fairs. The van will also be used for picking up organic fruits, vegetables and grains from other farms and vendors to process at the factory and to deliver to markets.
A28: Georgia Organic Peanut Association, Inc. | B28: Americus | C28: GA | D28: 31709 | E28: 2 | F28: 185399 | G28: Processing Capacity Expansion | H28: Enhancing the Value Chain for Certified Organic Peanuts in the Southeast | I28: The goal of this project is to create a new market and enhance the value of certified organic peanuts produced and processed in Georgia. The project will forge a new partnership between the Georgia Organic Peanut Association, a farmer-owned marketing cooperative, and Oliver Oil Company, a small family-owned processor of cold-pressed culinary oil. Together, they will acquire parallel processing equipment that will enable, for the first time in the Southeast, the production of Certified Organic peanut oil by expanding processing capacity and preventing commingling of organic and non-organic products. This new enterprise 17 will be supported by a joint marketing campaign to stimulate demand. As a result of the project, one processing facility and one storage facility will obtain organic certification for the first time, fostering a new local supply chain for Certified Organic commodities. Marketing through the Georgia Organic Peanut Association, farmers will increase the production, processing, and sales of Certified Organic peanuts grown in the region by 50%. The project will have a beneficial financial effect on no fewer than 15 farmers in the Southeast, including two beginning farmers and two socially disadvantaged producers, and create one new job.
... A33: Waiʻanae Community Re-Development Corporation | B33: Waianae | C33: HI | D33: 96792 | E33: 2 | F33: 1042574.9 | G33: Processing Capacity Expansion | H33: Realizing a 10-Fold Increase in Hawaiʻi Organic Food Production: Mechanization and Technology Advances in Food Processing Capabilities Across a Diversity of Organic Fruit and Vegetables. | I33: This project requests funding support to complete the last critical investment in processing which will enhance MA’O Organic Farms (MA’Os’) capabilities to handle 10x more products while maintaining and eventually increasing a 65-product inventory while providing greater food flow handling to ensure highquality product is distributed to a greater diversity of market segments. MA’O is currently in year five of a ten-year expansion effort, starting in 2018 and ending in 2027. Through this effort, MA’O is growing internship participation in its college-career farm leadership programs, increasing organic food processing, and creating new full time farmer positions. The goal of this project is to maximize processing capabilities within MAʻO’s newly constructed wash-pack facility, by introducing product inventory management and 19 food safety technologies. This will streamline and support MAʻO’s ability to handle 10 times more products, while maintaining and eventually increasing product inventory and throughput of organic produce to ensure products are distributed to a greater diversity of market segments. At the same time, the project will nurture community information exchange and capacity building in technology and food safety to train and empower new young leaders for Hawai’i’s organic sector. This increases the supply of organic fruits and vegetables in the Hawaiian Islands, where 85-90% of food is imported, and local organic food is in high demand.
A34: Kalona Creamery, LLC | B34: Kalona | C34: IA | D34: 52247 | E34: All | F34: 1999842 | G34: Processing Capacity Expansion | H34: Expanding Dairy Processing for Midwest Producers | I34: Kalona Creamery, LLC is requesting grant funds to expand organic milk production, handling, and processing capacity. This project will help expand the market for organic milk sourced from independent, small-scale dairy producers in Iowa, Missouri, Minnesota, and Wisconsin. Kalona Creamery sells branded organic milk products to retailers and distributors throughout the country. In addition, Kalona Creamery provides processing and milk handling services to a wide range of organic food companies in the upper Midwest. 23 This project will allow Kalona Creamery to increase processing services to organic dairy industry participants, including organic farmer-owned cooperatives and food companies. Grant funds will be spent on equipment to expand organic milk handling, storage, and processing capacity for organic milk, butter, yogurt, and cheese. Grant funds will also be spent on equipment to upgrade food-safety and wastewater handling programs in the company’s facilities. Ultimately, consumers will benefit from having increased access to high-quality organic dairy products sourced from small-scale, independent family farms.
A35: Andrew Miller | B35: SILVER CITY | C35: IA | D35: 51571 | E35: 4 | F35: 100000 | G35: Simplified Equipment | H35: Organic Oat Pre-Processing Equipment | I35: The goal of this project is to secure on-farm processing equipment to bring locally produced nutritious organic rolled oats to the consumer markets while preserving the product identity. For the past 2 years, A. Miller Farms and supply chain partners have searched locally for identity preserved organic rolled oats. This search has yielded no results implying a large market hole. With this grant A. Miller Farms can complete the initial pre-processing steps of hulling raw oats and separating them with a gravity table to distinguish the best quality for food grade specifications on-site. It can then finish processing these oat groats at Grain Place Foods in Marquette, NE, and bring the final product back to A. Miller Farms to distribute and market as organic identity preserved rolled oats. The Farm has a local distribution partner that already has demand for these identity preserved oats. Further market exploration will cover Iowa Schools and Hospital Systems. In addition, A. Miller Farms has also identified national retailers seeking identity preserved aspects that customers desire. Current processing of raw oats into a finished product at a small scale is not economically viable due to transportation costs to a dehuller facility and then to Grain Place Foods. Other consolidated commercial sources that have been identified are not able to process oats as identity preserved and do not intend to.
A36: levi Lyle | B36: keota | C36: IA | D36: 52248 | E36: All | F36: 100000 | G36: Simplified Equipment | H36: Aronia Berry Organic Puree | I36: Fresh aronia berries are the flagship of Levi Lyle’s business. Blueberry, cranberry, and cherry fruit industries operate under a business model that has not served the infant aronia berry industry well. Iowa farmers have had to export aronia to Michigan where processing infrastructure exists. These locations require consolidation of produce into 100,000 pounds to conduct a “small run” of concentrate juice or consolidation of 1,000,000 pounds to gain access to cleaning and freezing facilities. Further challenges in aggregation and financial risks larger startups undertake exacerbate these challenges. The success of this 1- acre organic certified aronia crop develops out of a strong identity in place-based food. The business has expanded from farmers markets into health-food stores. For this project, Levi Lyle is partnering with a 10- acre organic certified grower to expand his Aronia Berry Organic Purée. The goal for this Aronia business is to successfully market a shelf-stable product created from the whole fruit ingredient, currently unavailable. Unique purée will be bottled in 16 ounces for retail. The Aronia Berry Organic Puree Project will bottle 4,000 gallons of whole berry puree for retailers partnered with this Aronia business. Market feasibility studies demonstrate the products currently available use highly processed concentrated juice, which requires a greater cost to produce in small batches, separates the juice from the fiber, and minimizes aronia’s health benefits located in the fiber and polyphenols. This project will benefit the 100+ aronia producers in the region who are without a market by growing to serve the needs of a struggling aronia industry.
A37: Des Moines Industrial, LLC | B37: Des Moines | C37: IA | D37: 50317 | E37: 3 | F37: 3000000 | G37: Processing Capacity Expansion | H37: Organic Grain Gateway of Iowa | I37: The Organic Grain Gateway of Iowa (OGGI) project will help stabilize the organic grains and livestock feed supply chain. It will offer new market access for Iowa’s organic grain farmers, reduce reliance on imports for the coastal organic livestock markets, and ultimately increase organic grain production in Iowa. This will be achieved by assembling a dedicated organic grain aggregation and marketing terminal in central Iowa 24 with existing direct access to Norfolk Southern, BNSF and Union Pacific railroads the only site in Iowa with this connectivity. By the end of the project, Iowa’s organic corn and soybean farmers will see an increased demand for organic products, specifically on the East and West Coasts which currently rely on imports to meet regional demand for these products. By connecting these three critical railways in one location, centrally located in the largest producing state of organic corn and soybeans, organic farmers in the state of Iowa will have direct access to new markets. Together, with the support of Iowa organic farmers, USDA NOP TOPP Partners, the Iowa Department of Agriculture, and The Organic Trade Association, the project will be a crucial step in sustaining the growth of domestic organic production by providing the infrastructure and market access needed.
A38: Double Eagle Dairy, Inc. | B38: Murtaugh | C38: ID | D38: 83344 | E38: 2 | F38: 708000 | G38: Processing Capacity Expansion | H38: To create a marketplace for purchase and consumption of organic animal feed. | I38: The purpose of this project is to create a marketplace to sell organic feeds. Currently, a gap exists in the Idaho supply chain between organic commodities that are being grown in the area and the organic feed being consumed. Specialized machines and equipment are used to turn various organic commodities into 20 precise rations and mixtures for feeds. Farmers grow organic crops intended for animal feed but are unable to sell locally because the ability and/or capacity to process the organic commodity into animal feed is unavailable. Thus, the farmer resorts to selling crops to feed processors out of the area, causing the organic feed consumer to buy out of the area as well. This creates significant added costs for both buyer and seller. This project would address the supply chain issue directly. The activities to be performed are the purchase and installation of various machinery and equipment to be used to convert organic crops efficiently and accurately into precise animal feeds. This would enable to create a marketplace for organic animal feeds. The marketplace would create deliverable organic feed products that would include formulated pellets, total mixed rations, and processed commodities that could be used individually or incorporated into the customer's mixed ration for their feeding operation. The expected outcomes would be an increased processing capacity in the area for organic crop farmers and increased consumption of local organic feeds.
A39: North Sky Farm LLC | B39: Harvard | C39: IL | D39: 60033 | E39: 16 | F39: 627767 | G39: Processing Capacity Expansion | H39: Between a Farmers’ Market and a Hard Place: Getting Out From Under the Market Tent and Into the Supply Chain. Reinvigorating Our Local Organic Dairy Economy. | I39: The project goal is to increase farmstead creamery processing capacity and, in doing so, to create a milk market for other organic producers to sell their milk to the North Sky Farm creamery. With the increased processing volume, North Sky Farm will be able to meet the expectations of a wholesale distributor allowing them to sell organic cheese to many more people. The project will increase cheesemaking capacity so they are able to buy milk from another dairy farm in addition to processing milk from their own farm. The project team will rearrange creamery space to accommodate larger equipment, update the wastewater system to accommodate a larger volume, increase personnel to process the larger volume of cheese, and work with a consultant to sell the increased volume of cheese through a distributor. In addition, North Sky Farm is creating a milk market for another producer. Increasing processing will allow them to reach the minimum volume needed to work with wholesale cheese distributors which will bring organic cheese to a much broader customer base. This project would double processing capacity. There are three main expected outcomes: 1) milk contracts offered to two organic dairy farms, North Sky Farm’s own dairy and one other organic dairy thus creating a milk market, 2) processing will expand to a level to be able to sell through a wholesale distributor so their cheese will be able to be sold in mainstream grocery stores over a wide geographic area, and 3) an increase in sales volume to a level where the organic creamery is economically sustainable and is able to continue to employ at least four, and likely more fulltime employees beyond the end of the project period. North Sky Farm will achieve these goals by making some key changes to increase production capacity to remove processing facility equipment bottlenecks that curtail manufacturing capacity.
A40: ADELANTE CENTER FOR ENTREPRENEURSHIP | B40: WAUKEGAN | C40: IL | D40: 60085 | E40: 10 | F40: 1284315 | G40: Market Development and Promotion | H40: Cultivating New Organic Markets for Urban Farmers | I40: Adelante Center’s Garfield Produce (GFP) sustainable hydroponics urban farm produces premium quality microgreens for regional distribution in its clean facility located in one of Chicago’s most distressed West Side communities. Its products are sustainably grown year round and sold to local hotels, hospitals, universities, and restaurants through 7 regional wholesale distributors. Garfield Produce is the largest and most profitable minority and disabled veteran owned farm in the Chicagoland area. This project will allow Adelante Centers Garfield Produce to make the key investments that will facilitate the implementation of a consumer-facing retail organic microgreen product, including brand development, marketing, and product promotion in new and existing distribution channels. The project will also allow GFP to upgrade equipment to facilitate organic packaging, handling, food safety, and environmental controls will complement this project’s marketing and partnership focus for local urban organic producers. Adelante will facilitate a oneday conference to network existing rural and urban organic producers with organic buyers to share best agricultural practices, leverage collective facilities closer to the target market, and establish and test an alternative logistics supply chain to reduce costs and increase access to the Chicago (and other) nearby market(s). This will allow both Garfield Produce products and a more extensive list of smaller local organic producers to build collective capacity to grow into larger, more profitable, urban consumer markets. The project will include a feasibility study to assess the cost and benefit of expansion into new markets for organic products in Milwaukee, St. Louis, and Indianapolis. These programs will increase local urban agriculture jobs, expand business capacity, and allow organic products to reach local consumers who would otherwise never have access to nor understand the benefit of, organic produce.
A41: Wild Pansy Farm | B41: SEYMOUR | C41: IN | D41: 47274 | E41: 9 | F41: 929474 | G41: Processing Capacity Expansion | H41: Simply Indiana: Abundance to Share | I41: In early 2023, Wild Pansy Farm launched the Simply Indiana soup line, with support from a Specialty Crop Block Grant through the Indiana State Department of Agriculture. The company produces 60 gallons (600 servings) of soup weekly in a shared commercial kitchen, using beans and vegetables from a network of 10 Indiana and regional organic farms. Most of these farms are beginning farmer-, woman-, and or veteranowned. Wild Pansy Farm aims to expand processing to 1200 gallons per week by retrofitting the interior of an existing building and converting it into a purpose-designed soup manufacturing facility. This will help regional farms by providing a right-sized outlet to sell their organic produce at scale. Indiana Fresh Connect coordinates the delivery of Simply Indiana soup quarts to three food shelters in Jackson County, IN. By 22 moving to a purpose-designed processing space, Wild Pansy Farm can deliver to more food shelters. The new equipment will enable the soup to be served at schools in 18 southern Indiana counties, where eligibility for the Free and Reduced Lunch program is over 45%. Wild Pansy Farm will build annual processing capacity for $800,000 worth of produce and beans from the region’s organic growers, and configure the space to deliver 1,000,000 soup servings per year to its community, which is experiencing persistent poverty
A42: VALLEY MALT LLC | B42: Hadley | C42: MA | D42: 1035 | E42: 2 | F42: 3000000 | G42: Processing Capacity Expansion | H42: Northeast Organic Roller Mill (NORM) Project | I42: Valley Malt, DBA Ground Up, is a women-owned flour mill in Holyoke, MA proposing OMDG funding for a Northeast Organic Roller Mill (NORM) dedicated to Northeast organic grains. The project will increase processing capacity, reduce energy consumption, reduce labor, and capture a growing market demand for roller milled organic flour and organic baked products. The goals of the project would include 1) the installation of a roller mill system at the current Valley Malt, DBA Ground Up (VM/GU) facility by 2025; 2) the sourcing, marketing, and sales of 5 million pounds of roller milled flour annually by the end of the project; 3) the development of organic value-added products that create market demand and reach 28 underserved populations in the region. These goals will align with larger interventions that have been ongoing in the Northeast to explore regional markets and demand for organic food grains. Multi-state collaborations between the Northeast’s public and private sectors in the last 15 years have supported the development of cereal grain cultivars adapted to the Northeast that are favored by bakers and farmers alike. Regional resources from university extensions, agronomists, and peer-to-peer networks across the region will support growers in providing 2,600 acres of organic grains for this project. The project will benefit stakeholders from the entire Northeast grain value chain. This includes small and medium sized organic and transitional growers, distributors of organic foods, commercial bakeries, institutional buyers, micro-bakeries, specialty food producers from underserved populations, and approximately 300,000 consumers of organic food in the Northeast.
A43: Moon Valley Farm Inc | B43: Woodsboro | C43: MD | D43: 21798 | E43: 6 | F43: 100000 | G43: Simplified Equipment | H43: Moon Valley Farm's Organic Legume and Grain Capacity Expansion for Mid-Atlantic Producers | I43: This project will expand the capacity of Moon Valley Farm and its 40+ regional partner farms to grow, process, store and deliver organic legumes and grains to thousands of subscribers, direct market and wholesale customers across Maryland, Washington, D.C., and Virginia. Moon Valley Farm is a certified organic, year-round, diversified produce farm that grows legumes and grains on a small-scale and aggregates legume, grains, fruits, mushrooms, eggs and more from partner farms. The Farm wants to increase processing and aggregation of these crops to benefit its crop rotation plan, whole-farm planning, and to meet customers demand. However, the business lacks the equipment required to increase production, storage, and delivery of these specialty crops. Moon Valley Farm’s goals with this project are to expand capacity to process, aggregate, store and deliver high quality legumes and grains to meet regional customer demand with key pieces of equipment. This project will strengthen the community of farms, impact hundreds of acres, and increase the region’s food security and climate resilience.
A44: Aurora Mills & Farm LLC | B44: Linneus | C44: ME | D44: 4730 | E44: 2 | F44: 100000 | G44: Simplified Equipment | H44: Expanding soybean production capacity to strengthen Maine’s food systems and increase organic acreage by providing a market for profitable organic, food grade, regionally grown soybeans. | I44: Soybeans have been historically grown in the central United States, however, climate change is causing droughts in these areas and affecting yield. Maine is warming and has ample water supply, creating an increasingly ideal climate for soybeans. As a nitrogen-fixing crop, soybeans are an ideal rotation crop for other grains, providing nitrogen for the next year's crop and reducing the need for synthetic and manure fertilizers. Although Maine farmers want to produce more soybeans, they lack access to processing infrastructure to enable them to take advantage of the premium, food grade, organic soybean markets. Aurora Mills Farm (Aurora) is one of the leading organic small grains and legume growers in Maine. Aurora is also a value-added producer that processes and mills organic grains and legumes, providing flour, rolled oats, soybeans and field peas to numerous New England based institutions and food producers. Adding bean polishing, destoning and a second cleaner to create a gluten free cleaning line to the existing processing infrastructure will open up new market opportunities for Maine growers. They will be able to grow and access the organic soybean market by using Auroras processing infrastructure. Soybeans, the easiest legume to market, require a stain free, stone free bean. Increased weeds, inherent in organic production, contribute to more staining in the combining harvesting process. Aurora currently has the ability to remove the weeds in the cleaning process, but stained beans are still left. Polishing and destoning will provide Maine’s small grain and legume producers to access new gluten-free markets
A45: Renata Scarano | B45: Penobscot | C45: ME | D45: 4476 | E45: 2 | F45: 97509.26 | G45: Simplified Equipment | H45: Niche market creation with improved soil fertility reducing reliance of fertilizer inputs | I45: The economic viability of this farm is made stronger by the synergy of growing and marketing a legume such as edamame with two distinctive benefits: 1) the creation of a niche market for value-added fresh and frozen edamame, generating an additional diversified income benefit for the farm and 2) Utilizing the nitrogen-fixing ability of soybeans to fix and incorporate between 30 to 50 lbs. of nitrogen per acre into the soil. The project fulfills the need to purchase processing equipment and a transport van which plays a critical role in the storage and delivery of fresh and frozen edamame, ensuring the end product maintains the proper quality, safety, and shelf life throughout its final distribution channels such as long-established Farmers Markets and the numerous retail outlets the farm serves throughout the state of Maine
A46: BALFOUR FARM LLC | B46: PITTSFIELD | C46: ME | D46: 4967 | E46: 2 | F46: 99511 | G46: Simplified Equipment | H46: Growing Northeast Organic Cheese Supply by Expanding Farmstead Milk Processing | I46: This project's goal is to expand on-farm processing capacity to increase consumption of organic cheeses. To address the lack of availability of organic milk for purchase, Balfour Farm is expanding on-farm milk production to increase the farm’s on site processing. Proposed equipment purchases will replace existing equipment with larger capacity cheesemaking equipment to accommodate the planned 175% increase in milk production. The farm will increase the capacity for milk production from 12 cows to 20 cows by the end of 2025. The farm will replace the current oil-fired system, which is approximately 25 years old, with high efficiency propane system. This increases the volume of milk processed and reduces the time required per batch. A cleaner burning, efficient system will modernize process controls and be more a sustainable energy source.The automatic curd mill will solve two problems - workflow and employee fatigue. As more milk is processed, larger batches of cheese will take longer to mill the curds. The EBR curd mill will reduce curd cutting time. This will also reduce worker fatigue. The current hand operated mill places significant stress on the shoulder and arm joints while using. Replacing the mechanical cheese press with higher capacity pneumatic modelwill increase volume and provide for consistent process control, having a positive effect on product appearance, flavor, and texture.The farm’s increased organic milk processing will result in an annual cheese production increase of 7,745 lbs.
A47: Crystal Spring Community Farm, LLC | B47: Brunswick | C47: ME | D47: 4011 | E47: 1 | F47: 100000 | G47: Simplified Equipment | H47: Expanding Access and Capacity for Certified Organic Produce into Regional Grocery Markets with Custom Packaging | I47: This project will increase access for local organic products to large scale Northeast grocery chains by providing industry standard, cost effective, custom packaging of produce for small organic farms. Organic products in the Northeast and Mid-Atlantic regions are significantly underrepresented in large scale grocery markets where the vast majority of organic food products are sold. Small organic farms in the region do not have access to automated packaging machinery that can portion and pack bulk produce into retail size, industry standard UPC labelled units for large scale retail sale. Currently, small organic farms are packaging by hand into expensive small run packages. Reducing packaging costs will allow these farms to increase production volume and sales revenue. This project will allow the purchased, installed and calibration of equipment to provide custom packaging for four farms with the following goals 1)to increase the market share of organic products in large scale grocery stores throughout the Northeast, 2) to decrease 27 unit cost of small organic farm product packaging for retail grocery sales making these products more competitive while increasing sales volume, 3) to increase labor efficiency by reducing or eliminating low skill packaging tasks, and providing higher skill and ultimately higher value tasks for workers on organic farms, and 4) to foster and strengthen connections between small organic farms to develop shared pathways towards expanded markets.
A48: Maine Organic Farmers and Gardeners Association | B48: Unity | C48: ME | D48: 4988 | E48: 2 | F48: 639449.11 | G48: Market Development and Promotion | H48: Northeast Organic Dairy Market Development: Strengthening Consumer and Institutional Demand for Local Organic Dairy Products | I48: This project aims to strengthen consumer and institutional demand for local, organic dairy products produced in the Northeast (NE) US which face challenges such as contract cancellations and rising production costs. The project seeks to address this crisis by expanding the farm-to-institution market for organic dairy, increasing the number of retail outlets promoting organic dairy, and implementing targeted consumer marketing efforts to boost demand for products made with NE dairy. The first main activity is to increase grocery retail partners by onboarding food co-ops, independent grocers, and large-chain supermarkets committed to promoting and selling organic dairy from the Northeast. The Northeast Organic Family Farm Partnership (NOFFP) will develop compelling program pitch materials, increase staff support to onboard and retain Retail Partners, and establish a retail peer group to share best practices in promoting organic dairy. The second main goal is to facilitate product innovation for bulk organic dairy. For this goal, NOFFP will collaborate with regional farm-to-institution partners to increase the number of participating colleges, K-12s, and hospitals buying NE organic dairy. Strengthening relationships between buyers, distributors, and processors will enable market developments, including the introduction of bulk formats for organic yogurt, cheese, and fluid milk, in response to institutional buyer demands. The final goal is to develop a marketing campaign through the development of new marketing strategies to engage consumers and educate them about the benefits of NE organic dairy. This includes creating brand awareness and loyalty for local organic dairy brands through Point of Sale (POS) marketing, consumer food demos, social media, and targeted messaging. The project is expected to benefit more than 286 organic family farms and 30 value-added organic processors.
... A67: Anchor Ingredients Co., LLC | B67: Fargo | C67: ND | D67: 58104 | E67: 22 | F67: 2626181 | G67: Processing Capacity Expansion | H67: Anchor Processing Improvements | I67: The purpose of Anchor’s processing improvement project is to increase the market for US producers by expanding organic storage and processing capabilities across Anchor Ingredients Co., LLC’s ( Anchor) supply chain through improvement of current processes and installation of new equipment. This will be done through three activities. The first is to improve the product drags at internally owned facilities. This will allow for increased efficiency in moving organic products through value-add processing, storage, and inbound/outbound transit. Anchor’s current product drags cannot be operated in certain weather conditions which causes significant downtime. Additionally, these old/malfunctioning drags leak/spill product, causing additional work to re-clean spilled product as well as unnecessary loss of product. This goal will be completed over a two-week span at Hillsboro and Buffalo, ND locations in which the old drags will be disassembled, and the new clean product drags will be re-installed. The second activity is to install and update processing equipment, over six months. The new processing equipment will expand the channel for value-added organic products and increase organic storage capacity. Prior to Anchor acquiring the facility, it was not certified organic and didn’t have processing capabilities. The third activity is to create a new organic value-added product, by installing pelletizing processing equipment. Pelletizing hulls compresses the hulls into small, dense pellets. These pellets take up less space compared to loose hulls, allowing for more efficient storage and transportation. Pelletizing will increase Anchor’s storage capacity, and decrease the number of truck shipments to customers, as trailers are able to hold more pelletized product than non-pelletized product. It also allows customers to store these pelletized hulls more efficiently, thus creating additional capacity.
A68: Healthy Oilseeds, LLC | B68: Carrington | C68: ND | D68: 58421 | E68: All | F68: 100000 | G68: Simplified Equipment | H68: Organic Oilseed Processing Capacity Expansion | I68: Healthy Oilseeds is a small family-owned business that processes flaxseed, hempseed, borage, and other minor oilseeds. They cold press expel, mill, sift, and clean oilseeds. The products that come from processing are oils and protein, separating the organic oil from the organic protein. Healthy Oilseeds processes organic oilseeds 24 hours per day, 7 days per week and are not able to keep up with the demand for orders. The goal is to increase oilseed processing capability with the purchase of an additional head press increasing production to their facility. The expansion will also provide a larger organic market for organic producers to have another place to sell and market their organic crops. The upper Midwest is the key growing area for organic specialty oilseeds with Healthy Oilseeds being in the upper Midwest and buying directly from the producer. There is great demand for Healthy Oilseeds organic flaxseed and hempseed oil products grown and processed in the United States and they can supply these products that are certified USDA Organic and Primus Food Safety Certified. Organic producers and organic ingredient customers have trust in Healthy Oilseeds company and its products. The project will help supply the consumer demand and create a clear market channel for organic production of oilseeds to be processed close to where the seeds are grown.
A69: Westwick Farming LLC | B69: Lee | C69: NH | D69: 3861 | E69: 1 | F69: 77449.22 | G69: Simplified Equipment | H69: NH Grain Collaborative Organic Market Expansion | I69: The requested equipment is intended to significantly increase the amount of NH grown organic grain and value-added grain products available in the NH and Northeast market. In 2022, Westwick Farming LLC Tuckaway Farm received and conducted a USDA Value-Added Production planning proposal surveying the growing, harvest, post-harvest, processing, and market challenges in the NH grain shed along the mid-tier value chain and the potential of growing a NH Grain Collaborative. Appropriately scaled equipment was identified as a main bottleneck in meeting and expanding this market. This equipment will address identified gaps in grain transport, processing, and packaging capacity, all of which will allow growth in the 39 marketplace for organic grain farmers and value-added producers, and increased access to organic culinary grains for consumers.
A70: THE BUTCHER BLOCK, INC. DBA NORTH COUNTRY SMOKEHOUSE | B70: Claremont | C70: NH | D70: 3743 | E70: 2 | F70: 600000 | G70: Market Development and Promotion | H70: Fully Cooked Organic Bacon Innovation & Market Expansion Project | I70: North Country Smokehouse (NCS) is a vertically integrated organic meat producer committed to sustainable agriculture. The purpose of this project is to introduce two new innovative organic pork products to the domestic organic market, enhance the domestic organic supply chain, and support local economies by creating and retaining jobs. Through strategic product development, supply chain enhancement, and community engagement, the project aims to create improved market accessibility and awareness of organic meat products, thereby increasing demand and consumption. While the company currently produces more than 2 million pounds of organic meat annually, the proposed project is expected to increase production capacity by 175,000 pounds annually for three years. Activities include the procurement and installation of new processing equipment, development of distinctive packaging designs, and coordination of retail merchandising to optimize product visibility. Project activities will focus on strengthening the domestic organic supply chain and elevating public awareness about organic farming through an extensive, evidencebased marketing strategy consisting of print and digital advertising, public relations, and incentives offered to wholesale distributors. Community engagement efforts will involve collaborating with local staffing agencies and technical institutes to source local production talent, advertising job opportunities to the local Claremont community, and hiring and training local residents for new production and warehousing roles. The expected project outcomes include the introduction of innovative organic pork products to the market, creation of new, full-time employment opportunities, and enhanced public awareness about organic farming, animal welfare, and sustainability. Overall, the project intends to revolutionize the organic pork market, boost domestic organic supply chain, and create local jobs. These outcomes are expected to benefit producers, buyers, and consumers, making organic products more accessible, desirable, and appreciated nationwide. An estimated 4,000 producers, 11,000 buyers, and 15 million consumers will be informed about organic products, while 12 producers will increase, and 110 buyers will execute additional business transactions to meet increased demand.
A71: Two River Gourmet Mushrooms LLC | B71: Sea Bright | C71: NJ | D71: 7760 | E71: All | F71: 100000 | G71: Simplified Equipment | H71: Organic Horizons: Strengthening Rural Organic Specialty Mushroom Production, Processing, Infrastructure and Distribution | I71: The purpose of this project is to strengthen Two River Gourmet Mushrooms’ rural organic specialty mushroom processing, infrastructure, and distribution. Restaurants, supermarkets, and specialty stores increasingly offer organic mushroom products, creating a demand-driven market. However, there is a clearly defined challenge centered around expanding infrastructure and capacity as well as processing, storage, specialized equipment, and handling/shipping, which have not kept up with the demand for organic specialty mushrooms. The specialized equipment will allow Two River Gourmet Mushrooms to scale processing to meet local demand and ensure reliable, safe, and exclusive Organic Delivery of its product to expanding consumers. This equipment will make certain that they are able to scale production in successful processing of high-quality organic mushrooms, meeting the demands of the target market. The dedicated delivery van will break the market access barrier that exists because of handling/shipping bottlenecks. This will also greatly streamline supply chain processes, from harvest to distribution, to reduce post-harvest losses and ensure efficient delivery of organic mushrooms to consumers. These expanded capabilities will set an example of sustainable agricultural production. It will also allow for the generation of employment opportunities within the local community, including farm workers, technicians, and sales personnel. The project's success will contribute to the economic growth of the region.
A72: Sunny State Products Inc | B72: San Jon | C72: NM | D72: 88434 | E72: 3 | F72: 119612.25 | G72: Processing Capacity Expansion | H72: Add Technological Advancements to Organic Food Grade Grain Cleaning Facility | I72: Sunny State Products, Inc. (SSP) plans to add a high-capacity electric eye color and infrared (IR) sorter to enhance the ability to clean organic food grade grain crops. As the organic food processing industry has increasingly added higher technological equipment, the need to improve the quality of organic food grains has increased substantially. Adding a color/IR sorter will allow SSP to clean and transform organic grain to the high-quality standards required by the food grade grain industry. Organic grains typically have a higher percentage of foreign material, organic matter, diseased and unacceptable kernels due to the organic growing conditions. The addition of a higher technologically advanced machine will enable SSP to accept more organic crops and convert the crops to a usable organic commodity in the food grade grain industry. 41 This project will also reduce the processing cost of the plant to provide organic food grain at a cheaper cost to current customers and to market to new customers in the organic food grade grain market. SSP will be able to provide more organic grain and incorporate more organic farmers into their already large group of organic farms to make cheaper organic food grade grains possible. New York
A73: Breadtree Farms LLC | B73: Greenwich | C73: NY | D73: 12834 | E73: 21 | F73: 1957328 | G73: Processing Capacity Expansion | H73: Expanding the Market for Organic Chestnuts in the Northeast U.S. | I73: Breadtree Farms was founded in 2019 with a mission to build the organic chestnut industry to a watershed scale in the Northeast. This project will increase organic chestnut consumption by unlocking key gaps bottlenecks that currently constrain the growth of the Northeast organic chestnut industry. Chestnuts are a historically important, high-value staple food source that has been recently marginalized in the U.S. due to the 1904 introduction of c. parasitica (chestnut blight). A century of breeding has delivered hybrid trees well-suited for commercial organic production, which can yield 1,500-3,500 lbs./acre of a nutrient-dense, gluten-free perennial starch crop. Given growing consumer interest in grain alternatives, gluten-free 43 ingredients, and local/sustainable foods, Savanna Institute identifies a present-day market opportunity for a +50,000% increase over current production. A growing number of Northeast farmers (particularly historically underserved farmers) see organic chestnut agroforestry systems as a key strategy for diversifying agricultural landscapes and enterprises. The project will conduct a feasibility/technical development study for a best-in-class, global organic chestnut processing facility and complete key improvements to a Breadtree-owned, on-farm facility to deliver processing capacity for organic chestnuts. The project will allow the purchase and installation of specialized processing, handling, storage, and distribution equipment. Also, conducting outreach at buyer-engagement events, regional local food events festivals markets, product demonstration days targeted at handlers, organic consumar package goods, food advocacy marketing professionals-Increase regional producer coordination best practices through technical workshops, farm consultation visits, webinars, focused on best practices for product consistency, marketing, post-harvest processing coordination. Through this project, Breadtree and a national coalition of partners will address: the lack of existing in-region commercial processing capacity; demand for product development and strengthened supply-chain connections between buyers, consumers, handlers and producers; the need for improved supply-chain coordination between producers by building enhanced processing capacity, developing new paths-to-market, and engaging producers, while building relationships with consumers, handlers, and culinary professionals to increase market access and consumption. These interventions would transform the Northeast’s organic chestnut industry and contribute to important strategic growth of organic chestnut industries in other U.S. regions.
A74: Gianforte Farm LLC | B74: Cazenovia | C74: NY | D74: 13035 | E74: 22 | F74: 95173.92 | G74: Simplified Equipment | H74: Purchase of an on-farm grain storage system for value-added grains to help meet the demand for domestically and locally produced organic livestock feed and to enhance the local supply chain | I74: As capacity in the middle of the organic supply chain has not kept up with demand for organic products, there are a limited number of suppliers for feed grains in Central New York for dairy and livestock operations. These funds will be utilized to integrate a blower system, inventory scales, and supporting elements into the current operation at Gianforte Farm, LLC. While the facility currently grinds corn and soybeans for livestock feed, there is no efficient load out equipment for these feed commodities, leading to an overall lack of capacity and agility in the ability to supply current and future feed customers with organic feed. By integrating a continuous-flow system with the ability to efficiently load out, regional organic livestock and dairy producers will have an additional reliable, consistent, and competitive source of domestically/locally produced organic feed. This project enhances the regional organic supply chain and its resiliency, improves the local agricultural economy, and provides current and future feed buyers with additional options for purchasing domestic organic feed (which may be more cost-effective due to less transportation costs). In addition, this capacity expansion will result in an increase in purchasing of organic corn and soybeans from other local operations, thus enhancing the impact of this project while also keeping feed inputs local.
A75: Farmer Ground Flour, LLC | B75: Trumansburg | C75: NY | D75: 14886 | E75: 19 | F75: 99897.14 | G75: Simplified Equipment | H75: Increasing the processing capacity of food grade organic grains in New York State | I75: Farmer Ground Flour buys and processes a diversity of organic grain crops, paying a premium to local farmers and providing a market for organic crops not otherwise grown in New York. Farmer Ground Flour contracts with local farmers for hard wheat, which is traditionally grown in western states, to produce bread flour for the Northeast market. By shortening the supply chain and reducing food miles, the carbon footprint of their flour is reduced relative to the industry standard. This project will help Farmer Ground Flour increase its annual grain cleaning and milling capacity, increasing the volume of grain purchased. By upgrading grain cleaning and flour milling systems simultaneously, they will have greater capabilities from start to finish without bottlenecks. A new grain cleaner will enable Farmer Ground Flour to process crops for long-term storage efficiently and with less waste, and a new pair of mills will increase their hourly milling capability.
A76: Norwich Meadows Farm, LLC | B76: Norwich | C76: NY | D76: 13815 | E76: 19 | F76: 95261.08 | G76: Simplified Equipment | H76: Equipping a commercial kitchen at Norwich Meadows Farm for production of value added products from organic local vegetables and fruits | I76: Norwich Meadows Farm has been one of the most important suppliers of fresh, local, organic produce to the New York City region for more than two decades. The number of viable farms providing fresh local produce to this region is small and at risk of getting smaller due to intense pressure from national/global competition and increasingly difficult business conditions. It is safe to say that there is no other local farm providing the diversity, quality, and quantity of organic produce that Norwich Meadows Farm brings to 42 market each year. One key to their success has been continuous development of new markets, resulting in a uniquely diversified marketing program including direct sales at farmers’ markets, Community Supported Agriculture’s direct sales to restaurants and retail stores, and specialty wholesale distribution. Recently Norwich Meadows Farm has partnered with commercial kitchen operators and chefs to pilot a range of processed products using vegetables and fruits from the farm; these market tests have shown that there is a significant opportunity for unique organic processed products including sauces, purees, broths, dried/pickled products, and juices to be marketed through existing channels. They have already begun the process of building a 6,000+ square foot packinghouse; this structure will also be the home of a planned food hub. This project will allow for the purchase of equipment for a commercial kitchen to be in this building.
A77: Great Lakes Natural Fibers Inc | B77: Wooster | C77: OH | D77: 44691 | E77: 7 | F77: 99190 | G77: Simplified Equipment | H77: The use of wool as a natural alternative to synthetic weed barriers, a replacement for peat, vermiculite and perlite ingredients in organic potting mixes, and a medium for seed delivery | I77: The goal is to purchase wool equiment to create a market for wool in the horticultural industry to replace products currently used with more sustainable, certifiable organic products that will benefit both sheep and crop farmers. The only regional aggregator of wool from shearing has stopped buying wool. Sheep farming in Ohio is increasing, and with it, wool production. Coarse and low-grade wool can substitute soil amendments and weed suppression materials used in horticulture. Wool stores up to 33% of its weight in water and slowly releases water once the surrounding environment drops below 65% relative humidity, is fully degradable, contains Nitrogen, Calcium, Magnesium, Iron, Sulfur, and other Micro Nutrients. Felted wool mats can replace plastic weed barriers. They can regulate soil temperatures, prevent moisture loss, add fertilizer, act as a pest barrier to slugs and snails, and provide excellent weed prevention. Shredded wool can be mixed with seed to be a delivery method for habitat restoration, landscaping, and crop establishment. Soil and potting mixes are currently amended with peat, vermiculite, and perlite to increase the water-holding capacity and provide aeration. Adverse ecological impacts resulting from to these soil amendments include the depletion of peat bogs and the high carbon footprint of vermiculite and perlite from transportation and overseas mining operations. Wool pellets can provide aeration, hold moisture, and are naturally high in nitrogen making them the perfect slow-release, all-natural fertilizer.
A78: Grange Cooperative | B78: White City | C78: OR | D78: 97503 | E78: 2 | F78: 1500000 | G78: Processing Capacity Expansion | H78: Expanding Processing and Marketing Capacity for Organic Grain for Livestock Feed | I78: In 2022, U.S. farmers produced more than 2.35 billion tons of grain feed to serve domestic and international livestock producers (USDA Economic Research Service). Still, less than 1% of the grain feed produced in the United States is organic, despite strong and consistent growth in U.S. demand for organic food. With more than 82% of U.S. households buying organic products regularly (Organic Trade Association), the Organic Center notes that driven by growth in demand for U.S. organic livestock feed the U.S. has become a substantial net importer of organic products. In fact, U.S. imports of grain feed have steadily increased over the past decade, growing from 40% in the 2011/2012 crop year to 60% in the 2021/2022 crop year. This is primarily due to the major barriers that exist to producing, processing, and marketing organic grain feed, namely higher costs of production and lack of processing and marketing infrastructure. To meet current U.S. consumer demand and expand opportunities to build the U.S. organic grain feed market, Grange Cooperative will perform the following activities: 1) expand its processing capacity to create more and better markets for organic producers and 2) execute marketing and promotional activities that will help to build commercial markets for U.S. organic grain feed products. This project’s goals (deliverables and expected outcomes) include achieving 2,000 additional tons of organic grain feed processed and a $1,655,000 increase in domestic organic grain feed sales by the end of the project period.
A79: Camas Country Mill, LLC | B79: Eugene | C79: OR | D79: 97402 | E79: All | F79: 99999 | G79: Simplified Equipment | H79: Pearler for Organic Growth | I79: Camas County Mill has been certified organic since inception of the mill in 2011. Organic is an important and rapidly expanding part of their mill business. Organic farming is important to Camas County Mill because it provides wholesome food to people with minimal disruption to the soil. Camas County Mill currently processes organic wheat, spelt, rye, emmer, oats, and buckwheat. These are all milled into flour as well as flakes. Currently, they operate four 950mm Engsko mills producing flour as well as a Roastech roaster flaker that produces flaked grains. This project will allow Camas County Mills to purchase equipment to meet increasing demand for healthier organic options. They are currently providing the grains intact with hull and bran to consumers. Having the ability to dehull and pearl barley themselves will 45 increase their organic offerings. The goals of this project include: 1) increasing interest and access to ancient grains in the form of pearled organic grains, 2) furthering organic grower base with organic crop options, 3) increasing resiliency of Camas County Mill and other organic farms, and 4) increasing consumer access to organic meat. This project will allow Camas County Mill to increase annual gross income, increase processing capacity by 15%, and increase the number of organic products processed by 125,000 pounds.
A80: Oregon Organic Coalition | B80: Lyons | C80: OR | D80: 97358 | E80: All | F80: 547600 | G80: Market Development and Promotion | H80: Growing Markets for Pacific Northwest Organic Products | I80: The Oregon Organic Coalition will lead a multi-sector project to grow the market for organic products from the Pacific Northwest (PNW). This project represents a major collaboration with partners including the Oregon Department of Agriculture, Organically Grown Company, Hummingbird Wholesale, the Good Food Foundation, Tilth Alliance, the Oregon Farm-to-School & School Garden Network, and others to promote Oregon and Washington-produced organic food and strengthen organic market channels. Its purpose is to drive consumer demand for organic products and expand valuable markets for organic producers, targeting the specialty/craft food and farm-to-school markets. While building organic market position across the entire food sector, it will focus on products with identified opportunities for significant growth, including barley and other grains, fruits and vegetables, hazelnuts, and wine grapes. Key activities will include assisting organic producers to become market-ready for wholesale sales, supporting their attendance at trade shows, and connecting them to buyers with values-based purchasing goals. Partners will also conduct strategic communications to educate consumers about the organic label and the benefits of organic food, strengthen organic food in the PNW identity and brand image, and build demand for crops and varieties that are regionally adapted, high-performing, and profitable for organic producers. The project will benefit organic producers through improved value chain coordination, promotion, and increased connections to high-value markets. It will also benefit small and mid-scale craft food manufacturing businesses, people served by farm-to-institution programs, and the public, through greater access to organically produced food.
A81: Cascade Pacific Resource Conservation and Development | B81: Corvallis | C81: OR | D81: 97339 | E81: 1 | F81: 191373.42 | G81: Market Development and Promotion | H81: Organic Hazelnut Market Development | I81: The Oregon Organic Hazelnut Collective (OOHC) will develop a brand for Oregon Organic Hazelnuts and create educational marketing materials to be distributed to stakeholders in the hazelnut industry as well as to food and health influencers. The project objectives include 1) creating and distributing branded educational materials on the benefits of domestically grown organic hazelnuts in comparison to similar products 2) securing long-term customers that can purchase large volumes of hazelnuts each year through events and marketing campaigns for restaurants, community markets, influencers, etc. and 3) addressing 46 the infrastructure bottleneck in the supply chain. These materials would 1) educate stakeholders and consumers on the ethical and environmental issues surrounding imported nuts 2) advertise the health and environmental benefits of organic hazelnuts versus other nuts and nonorganic hazelnuts, and 3) ensure that consumers who purchase products with this label know that their hazelnuts originate from domestic, sustainable, and ethical sources. With these branded educational materials, the OOHC will increase the visibility of this crop at local markets, festivals, and food and health fairs. With an increased public presence, OOHC aims to establish lasting relationships between health and environmental influencers, American hazelnut growers, and small business owners, who can purchase larger quantities of hazelnuts each year. Effective branding, distribution of marketing materials, and events showcasing organic hazelnuts will have the long-term effect of addressing infrastructure bottleneck issues that currently exist in the supply chain. While hazelnut farmers can increase their harvest, when they attempt to develop independent sales channels, they are turned away by processors who are not interested in shelling and returning small batches of hazelnuts. With an increased demand in the market, there would be an opportunity for farmers to increase their production and for a new processing plant devoted to organics to come online.
A82: Pocono Organics, LLC | B82: Long Pond | C82: PA | D82: 18334 | E82: All | F82: 69482.81 | G82: Simplified Equipment | H82: Post-Harvest Handling Equipment for Regenerative Organic Certified Microgreens Powder (PowerGreens) | I82: Pocono Organics intends to increase the production of Regenerative Organic Certified (ROC) microgreens for processing into a value-added freeze-dried microgreen powder called PowerGreens. The processing method, combined with appropriate packaging systems, extends the microgreens’ shelf life exponentially, maintains their high-nutritive attributes, protects the product’s food safety, and supports the product quality of an innovative organic product. The equipment requested for processing and packaging will expand product market potential to nationwide retail and wholesale outlets through unique channels. It will ensure the shelf stability of increased production quantities and reduce energy consumption for storage and distribution by eliminating refrigeration needs. The product will be sold directly to consumers through physical and online stores and additional regional and national retailers. Various sized packaging options will expand organic market opportunities for wholesale target markets including juice bars, fitness centers, bakeries, dietary supplement companies, and health care institutions. A mixture of hemp, broccoli, and sunflower microgreens are grown in two-week successions, year-round using greenhouse operations. This production system supports the USDA’s climate smart action goals by minimizing water usage and carbon emissions in a controlled indoor environment. The PowerGreens processing results in a nutrient-rich organic food source that can be produced and aggregated throughout the entire year, providing expanded market opportunity to organic farmers during colder months and creating strong supply chain security. The equipment requested will improve production and processing efficiencies resulting in minimal product loss, safe product preservation, and expanded organic market potential.
A83: Pa Flax Project | B83: Pottstown | C83: PA | D83: 19465 | E83: 6 | F83: 1681187 | G83: Market Development and Promotion | H83: reestablishing the fiber flax industry in Pennsylvania answer to 14 Pennsylvania and greater Mid-Atlantic | I83: The PA Flax Project (PAFP) is a woman-owned cooperative business whose mission is to reestablish the fiber flax industry in Pennsylvania by initiating new organic production and processing capacity. Through this project, PAFP will engage with the beginning, middle, and end of the fiber flax supply chain. Growing high-quality fiber flax has a proven history in Pennsylvania, yet there is little to no infrastructure dedicated to the harvest and post-farm processing of fiber flax in the country – often called the ‘missing middle’. As it stands, PAFP sees no way to bring Pennsylvania's fiber flax to market. PAFP will support and educate producers, and work to build out the middle of the supply chain bringing Pennsylvania's organic flax for linen to market through planning and research of a long line fiber flax scutching mill. PAFP envisions this cooperatively owned mill providing an additional income stream to producers after their crop leaves the farm. With the support of partners, PAFP hopes to open the door to this high-value market for Pennsylvania farmers and manufacturers, putting 12,000 acres of organic fiber flax into production. PAFP will leverage its industry connections to establish contracts for domestic and international buyers of fiber flax and coproducts produced in its cooperatively owned mill. This project aims to establish the first complete organic fiber flax supply chain in the Eastern U.S.
A84: TUSCARORA GRAIN CO LLC | B84: MOHRSVILLE | C84: PA | D84: 19541 | E84: All | F84: 100000 | G84: Simplified Equipment | H84: The Harnessing Organic Market Expansion through Pelletizing Assistance (Home PA) Project | I84: Tuscarora Grain CO LLC (TGC) will purchase and install a Century Pellet Mill. This mill will increase local capacity for pelletizing currently underutilized organic byproducts into new value-added products with ready markets. The project will build the organic livestock feed supply chain capacity, remove barriers to new organic market development, and benefit organic producers by accomplishing the following: Objective 1: Install organic-approved pelletizing equipment capable of processing 24 tons per day. Objective 2: Improve organic supply chain capacity and organic product development in Pennsylvania by providing thirdparty processing to local organic producers and feed mills. Objective 3: Increase the Pennsylvania organic community’s access to organic amendment by 2.500 tons per year. These objectives will empower local organic grain producers and feed mills to engage with new markets through access to previously unavailable contract pelletizing. It will create a new market for domestically produced organic byproducts 48 by expanding TGCs capacity for processing, aggregation, and distribution. Additionally, it will reduce potential waste from grain and animal processing by offering value-added product development opportunities.
A85: Snipes Farm and Education Center | B85: Morrisville | C85: PA | D85: 19067 | E85: All | F85: 24318.13 | G85: Simplified Equipment | H85: Snipes Farm Organic Market Development Program | I85: Snipes Farm and Education Center requests funds to produce organic, value-added products. Snipes Farm is USDA/PCO Certified Organic and runs a successful on-farm market and Community Supported Agriculture (CSA) membership program. The Center has organic produce contracts with senior centers, hospitals, and social service agencies, to address hunger relief and food insecurity in the region. Snipes has experienced increased demand for its organic produce over the past 5 years and needs to add organic value-added products to their offerings. Products include tomato & hot sauces, applesauce, berry jams, pickled vegetables, teas, herbs, herbal products, and dehydrated products. Improved equipment will initiate the 49 production of value-added organic products for its customers. In the past 5 years the Center’s overall organic produce sales increased 20%. At their on-farm market, Snipes sells value-added products bought in from other local farms and producers (honey, syrup, apple butters, herbal products), but none are certified organic. As one of the few certified organic farms in the area, the Center is well positioned to meet customer demand for organic value-added products, except for the for lack of efficient production equipment. The Center’s overall organic vegetable sales have increased 155% since 2015 due to contracts to grow and deliver food. They employ regenerative agriculture methods to address soil health and climate change concerns.
A86: JONESTOWN FARM ENTERPRISES, LLC | B86: Brackney | C86: PA | D86: 18812 | E86: All | F86: 670214.6 | G86: Market Development and Promotion | H86: Optimizing and Expanding the Organic Farmgate to Fork Ecosystem in Southeastern North Carolina | I86: The proposed project outlines a transformative shared-services Farmgate-to-Market channel marketing system in Southeastern North Carolina, focusing on the constrained availability of organic crops. The initiative targets small, beginning, disadvantaged, and BIPOC farmers, strategically addressing economic disparities, social equity, and sustainable farming practices. The project aims to empower underserved communities, stimulate economic growth, and enhance climate-smart agriculture. Centered on a 150-mile radius from Wallace, NC, the project targets an area with low per capita income and a significant BIPOC population. It aims to fill market gaps for limited-availability organic crops like specialty beans, peppers, and herbs. By establishing a shared-services model, the project fosters collaboration among farmers, providing access to resources, transportation, marketing, and expertise. This approach empowers farmers, enhances efficiency, and reduces costs, ensuring direct market channels and incentives for organic producers. Partnerships with local organizations, agricultural offices, and community leaders ensure engagement and address historic disparities. The project supports disadvantaged communities by connecting farmers directly to purchasers, expanding markets, and increasing consumption of locally produced organic products. The project boasts a seasoned team with expertise in agriculture, supply chains, and marketing, collaborating with local partners for a holistic approach. Overall, the project aims to create a lasting positive impact by empowering marginalized farmers, fostering sustainability, and promoting equity opportunities in Southeastern North Carolina.
A87: Plants to Food, LLC | B87: Lincoln | C87: RI | D87: 2864 | E87: All | F87: 100000 | G87: Simplified Equipment | H87: Plants to Food Equipment Expansion Project | I87: Plants to Food is a manufacturing service partner for plant-based food brands. They bring over 25 years of manufacturing expertise and excellence in the areas of product formulation, testing, labeling, packaging, distribution, and more. Plants to Food has been cooking, blending, infusing, and packaging premium food products for over 25 years. In addition to product and packaging capabilities, they also offer R&D, labels, and nutritional software that creates nutrition fax panels per FDA guidelines. Plants to Food’s temperaturecontrolled production facility is state-of-the-art with an innovative warehouse management process. This includes a dedicated pick and pack fulfillment line for direct-to-consumer and a separate pallet racking system for storage and carrier pallet loads. As the company continues to expand, they are constantly looking for new ways to accommodate growing demands. This project will include the purchase of a Rotary Fill and Seal Machine for Premade Doypack as well as a Piston Filler for Liquids and Pastes. This machine will increase processing by roughly 12,000 units per month. It will allow Plants to Food to take on seven new customers and supply four new jobs at its factory. Overall, Plants to Food will see a 10% increase in processing with this new machinery. With this purchase, its factory will see an increase in processing capacity by 4,500 pounds a month. As Plants to Food continues to grow, it receives an influx of orders beyond what the facility can currently produce. As a co-manufacturing business, this new equipment will not only help expand Plants to Food processing but also the processing of the various organic food companies they are partnered with.
A88: Berrybrook Organics LLC | B88: Marion | C88: SD | D88: 57043 | E88: 1 | F88: 96214 | G88: Simplified Equipment | H88: Alleviating Organic Egg Supply Chain Bottlenecks and Increasing Production Efficiency | I88: Berrybrook Organics, LLC (Berrybrook) is a certified organic farm and value-added processing company. Throughout their 24 years producing and marketing organic value-added grains, meats, and eggs, their reputation for product quality and consistency has earned them a loyal customer base, extensive marketing experience, and valuable relationships with wholesale clients. The equipment requested addresses two needs: supply chain management/improvement through the purchase of a delivery vehicle, and processing efficiency through the purchase of an Egg Grader machine for organic egg processing. Berrybrook currently supplies Grade A organic eggs to two local grocery stores and nine Sioux Falls wholesale and retail customers. Last year, about 95% of total eggs produced were sold to these outlets. In addressing these two areas of need, Berrybrook will reach new organic markets, increase processing efficiency for their organic goods, and ensure a quality, safe organic product to consumers.
A89: Tiffany Leigh Stanley (A Different Chick Farm & Orchard) | B89: JOHNSON CITY | C89: TN | D89: 37604 | E89: All | F89: 99900.22 | G89: Simplified Equipment | H89: Equipment needed to produce a higher volume of our Organic Pepper products such as Hot Sauce, Jelly, and Seasonings so that we can use excess items that are not sold for Organic Value added products. | I89: A Different Chick Farm and Orchard (ADCFO) has been growing produce since 2016 and has been certified organic since 2020. They are known for their hot pepper processing and have developed a line of spice blends, hot sauces, and pepper jelly made from their produce. The processing of these products can easily triple the value of the produce over fresh sales alone. The goals of this project are to purchase equipment to allow for greater processing volume of hot sauces and spice blends and deliver them to a wider geographic region in northeast Tennessee, western North Carolina, and southwest Virginia, including regional grocery outlets. This project aligns with the program purpose by increasing domestic organic supply chain capacity, expanding capacity for processing, and improving the ability to comply with regulatory requirements and quality standards. Additionally, it will allow access to processing equipment for other organic producers in the area.
A90: RKH GIN LLC, dba Woolam Gin | B90: O'Donnell | C90: TX | D90: 79351 | E90: 19 | F90: 3000000 | G90: Processing Capacity Expansion | H90: Expanding Capacity and improved quality of Organic Cotton. | I90: RKH Gin LLC, dba Woolam Gin is a primarily woman owned ginning facility that has processed organic cotton for 33 years, being the first United States to do so. It is located in a high poverty area in Lynn County, Texas and serves other high poverty areas including Dawson and Terry Counties. Woolam Gin is seeking a grant award to purchase and install equipment to expand the services and improve processing to increase production of organic cotton for farmers which will improve overall market production of the beneficial product. The overarching project purpose is to improve efficiency, therefore improving outcomes for farmers and the organic market. The equipment will increase production from 25 bales an hour to up to 40 bales an hour. The increase in processing will improve the housing time of cotton in the warehouse which will improve the grades and facilitate earlier entry into the marketplace, benefiting farm producers, processors, and consumers. The faster processing will improve turnaround for the farmer and further increase production possibilities. The primary partners and collaborators of the project will include participating organic farmers, the project manager, project supervisor, gin manager and other supporting human resources workers. This grant award will create improved markets and expand processing capacity which in turn will enrich market availability and further development of production resources and production.
A91: Steelbow Farm LLC | B91: Austin | C91: TX | D91: 78721 | E91: 35 | F91: 90372.62 | G91: Simplified Equipment | H91: Steelbow Farm: Expanding Access to Local, Organic Produce in Central Texas | I91: Steelbow Farm is seeking to broaden its delivery range and increase local food access and supply chain resilience by procuring a delivery vehicle. The overarching purpose of the proposed project is to expand access to local, organic produce by eliminating the current constraint of distance and delivery radius, while simultaneously addressing the growing demand for product in the current marketplace. Currently, Steelbow Farm has demand for their product that exceeds their capacity because they do not have a vehicle and therefore have a limited delivery range. This bottleneck is hampering Steelbow Farm’s ability to rise to the organic market demands. They believe access to this equipment would drastically improve access to organic produce, as they could radically increase their customer base and range. For context, currently, within Travis County, only .06% of food is produced locally. The Austin and Travis County areas are seeing a decline in the amount of vegetable farms and farmland, which are disappearing at an alarming 16.8 acres a day. Amidst these startling statistics, this business is thriving and demand for their produce is extremely high. Steelbow Farm wants to be able to meet the market demand and fill the gap within the local food system. As organic vegetable producers, they are striving to increase the percentage of local food consumed within their community.
A92: Armagh Fine Foods LLC dba Armagh Creamery | B92: Dublin | C92: TX | D92: 76446 | E92: 25 | F92: 100000 | G92: Simplified Equipment | H92: Enhancing Organic Dairy Production and Market Access in Texas | I92: The primary goal of this project is to enhance and expand the production capabilities of Armagh Creamery organic farming and dairy operations. By acquiring essential equipment, the project aims to achieve increased efficiency, product diversification, and expanded distribution. This equipment will enable Armagh Creamery to venture into new product lines, including heavy cream and butter, expand production of existing products, and streamline the production process, reducing the workload on current employees and enhancing overall efficiency for creating new butter product lines. The acquisition of a delivery vehicle will significantly improve distribution capabilities, allowing Armagh Creamery to reach local retailers and drop locations in Central, North, and West Texas. This expansion will promote the availability of organic dairy products to a wider consumer base. The specific objectives of this project are two-fold: 1) to scale yogurt production to the full daily capacity of 10,000 units per day, two days a week. This increase will enable the creamery to supply more retailers throughout Texas and cater to the growing demand in the direct-toconsumer market and 2) to expand raw milk and cream production to 600 gallons a day for 3-4 days a week, resulting in a weekly output of 1800 to 2400 gallons. This expansion will further support the directto-consumer market and provide ample resources for the planned heavy cream and butter product lines.
A93: Triple J Organics, LLC | B93: Mission | C93: TX | D93: 78572 | E93: 15 | F93: 66645 | G93: Simplified Equipment | H93: Diversifying Organic Supply Chains for Small Producers in the Rio Grande Valley | I93: Triple J Organics is a minority-owned certified organic citrus orchard in Mission, Texas established in 1995. Triple J manages 25 acres of certified organic citrus groves, primarily of Ruby Red grapefruit and early season oranges, as well as Navel Oranges, Meyer Lemons, Tangerines, and Tangelos in smaller quantities. This project will increase consumption of locally produced organic orange juice in the Rio Grande Valley and increase the profitability and long-term viability of Triple J Organics through special purpose equipment purchases that allow Triple J to process 32,000 lbs. of “waste”, or seconds, oranges into fresh juice and deliver it safely to customers in the Valley. The project will target school districts as potential customers, as well as supermarkets, restaurants, health food stores, daycare facilities, and eldercare facilities as needed. Beneficiaries include Triple J Organics, local schools and businesses who purchase the new product, as well as other organic citrus growers in the Valley who may be able to cooperate and aggregate to produce a higher margin value-added product.
A94: Texas Department of Agriculture | B94: Austin | C94: TX | D94: 78701 | E94: 37 | F94: 197603.77 | G94: Market Development and Promotion | H94: Texas Organic Market Development & Promotion | I94: The Texas Department of Agriculture (TDA) will use a multi-faceted approach to promote local organic producers in the produce, grains, dairy, and fiber markets. Though these industries are each unique in their production, the issues they experience are similar. These challenges include, but are not limited to, lack of knowledge among consumers of each industry’s availability/benefits, existing gaps between producers and buyers that result in barriers for growth, and an absence of public resources that assist organic farmers from promoting themselves more efficiently. Through this project, TDA will increase local consumer knowledge, support activities to develop new markets, increase demand for domestically produced organic agricultural products, and provide additional market paths for organic farmers in Texas. Goals of this project include: 1) increase public knowledge of Texas organic agriculture industry, 2) provide opportunities to improve market share and sales of local organic producers, and 3) build new connections between Texas producers and potential buyers to accomplish these goals. TDA Marketing will produce new marketing materials targeted for the organic industry, assist organic producers with attending trade shows relevant to their respective industries, facilitate business to business interactions, and run a social media campaign that highlights each industry. These activities will strengthen the relationships between Texas organic 54 crop/product producers and buyers, as well as better inform the public on the availability and benefits of Texas organic products. These relationships would aid in ongoing efforts to strengthen the supply chain, build on current opportunities with Texas agriculture associations, assist historically underserved communities, and increase demand for locally produced organic products. To further assist the organic industries of Texas, TDA will assist in the production of the Field View Organics program. This program aims to identify organic operations across the state and mark them for aerial spraying companies to help prevent potential chemical drift or contamination of organic crops. By supporting this initiative, TDA will protect the current organic producers across the state and alleviate potential concerns for new members wanting to enter the industry.
A95: Yaupon Holly Tea, LLC | B95: Cat Spring | C95: TX | D95: 78933 | E95: 10 | F95: 801330 | G95: Market Development and Promotion | H95: Promotion of organic yaupon tea as a domestic alternative to imported tea distributed to the foodservice industry. | I95: This project aims to increase the American consumer awareness of organic yaupon tea as a replacement for imported tea via the food service sector. An Organic Yaupon Marketing Plan will increase opportunities for consumer exposure to organic yaupon tea while also allowing for additional customers, buyers, and parties to participate in the domestic organic yaupon tea industry. Yaupon is a caffeinated plant native to North America and rich in polyphenols and antioxidants like imported tea. By using a hybrid of traditional tea preparation methods, organic yaupon tea has an almost indistinguishable flavor profile from imported green and black tea served in both hot and iced tea. Cat Spring Yaupon has created a cohesive marketing and outreach plan to increase the amount of organic yaupon tea served in restaurants, cafes, hotels, and spas. This plan incorporates the opportunity to promote and support additional organic yaupon producers through the American Yaupon Association while also supplying to tea companies who would otherwise be selling imported tea to their food service customers. This will also allow restaurants to substitute imported tea on their menus with organic yaupon tea thus giving their customers and guests an opportunity to sample and fall in love with the incredible domestic organic yaupon tea.
A96: Spicy Organic LLC | B96: Frisco | C96: TX | D96: 75035 | E96: All | F96: 93866.76 | G96: Simplified Equipment | H96: Grant for Simplified Equipment's Projects to Increase Efficiency and Output. | I96: Spicy Organic LLC, a dedicated provider of premium organic spices, herbs, and grains, proposes to purchase and install machinery equipment to streamline its production processes, enhance efficiency, and expand market reach. The proposed equipment will significantly boost processing capabilities, reduce manual labor, and improve the availability of organic ingredients in both domestic and emerging markets. By introducing a semi-automatic auger filler machine, production output is projected to increase substantially from 60 pouches to 900 pouches per hour. This advancement will not only result in enhanced efficiency and productivity but also bolster the domestic market demand for the company’s organic ingredients. The Band Sealer will mark a significant leap towards improving overall efficiency and output. As pouches are sealed seamlessly and rapidly, Spicy Organic anticipates an increase in processing efficiency, enabling them to explore untapped markets and create new avenues for expanding the demand for their organic ingredients. The inclusion of a forklift machine will revolutionize this aspect of the company’s operations. With the ability to efficiently move and store organic ingredients, Spicy Organic expects a notable surge in production output. The inkjet coding machine and conveyor system are poised to streamline this process, augmenting efficiency, and output. This will ensure precise and timely labeling, bolstering the availability and marketability of their products within the domestic market. The proposed enhancements will not only elevate processing efficiency but also facilitate entry into untapped markets, increasing the demand for Spicy Organic’s premium organic ingredients.
A97: Organic Marketing Institute | B97: Sterling | C97: VA | D97: 20165 | E97: 10 | F97: 722500 | G97: Processing Capacity Expansion | H97: Increasing Awareness of Third-party Grass-Fed Organic Certification to Increase Demand and Consumption of Grass-Fed Organic Dairy | I97: The Organic Marketing Institute (OMI) expands the marketplace for organic agricultural products by supporting innovative certification programs that extend the third-party organic certification baseline into novel product categories. OMI promotes third-party certifications that enhance National Organic Program (NOP) standards and offer transparency and full supply chain traceability while benefiting the environment. The Organic Plus Trust (OPT) Certified Grass-Fed Organic Livestock Program has set the first national standard for grass-fed, organic ruminant livestock production for meat and dairy that builds upon USDAcertified organic dairy standards and helps differentiate farmers’ products. An end-to-end, third-party certification, it verifies all production and handling of certified products from farm through processing to sale. Grass-fed Organic Certification has seen initial producer interest and customer satisfaction due to the market stability, transparency, trust, and climate benefits of the products certified. There is demonstrated need and opportunity to scale the certification as a value add for organic producers, retailers, and customers. With funding from USDA, OMI will support farmers and brands, having the OPT Grass-Fed Organic Certification, with expanded marketing and promotional support. OMI will do this by enhancing supplier relationships, creating a marketing strategy that promotes the climate benefits, third-party integrity, full-supply chain traceability and regenerative characteristics of the products, and executing robust consumer marketing efforts. With these efforts, to grow the market for Grass-Fed, organic dairy products, supporting an additional 50 farmers per year and engaging an additional 10 brands over the course of the grant.
A98: Thornhill Farm, LLC | B98: Greensboro Bend | C98: VT | D98: 5842 | E98: 4 | F98: 48552.6 | G98: Simplified Equipment | H98: Grain drying & cleaning equipment for Thornhill Farm, LLC grain center | I98: Grain farming is returning to the region, and the tide is rising. There are a growing number of bakeries and distilleries in Vermont and the region needs organic grain that is grown and processed locally. Many farmers cannot grow grain because they lack the capacity to clean, dry, and/or store grain. The grain drying machine and grain cleaning machine will be a great help and be used to process the grain of many farms. The purchase and installation of more efficient grain drying and cleaning equipment to replace less efficient equipment and hand labor will allow Thornhill Farm to 1) accept and purchase more organic grain from farmers on the day of harvest, and after, to dry and clean the grain, 2) to support the re-emergence of local and regional grain production in Vermont, New York, and Maine, 3) to inc usrease local organic grain market availability by making a greater amount of grain and flour available on the market for baking and spirits, and 4) to ultimately, support Northeastern grain farmers, organic agronomy and soil health, and increase regional grain markets, all of which help mitigate climate impacts through reducing climate miles, increasing organic agronomy practices, reducing exposure to flooding and drought through water-soil interactions, and sequestering carbon.
